[
  {
    "BreweryName": "Mountain Hawk",
    "Location": "United States"
  },
  {
    "BreweryName": "Mountain Heart Brewing",
    "Location": "Carbondale, CO United States"
  },
  {
    "BreweryName": "Mountain Heights",
    "Location": "United States"
  },
  {
    "BreweryName": "Mountain High Seltzer",
    "Location": "Lovingston, VA United States"
  },
  {
    "BreweryName": "Mountain Hops Brewhouse",
    "Location": "Casper, WY United States"
  },
  {
    "BreweryName": "Mountain Hops Brewing (Kyle Collins)",
    "Location": "United States"
  },
  {
    "BreweryName": "Mountain House Trading Company",
    "Location": "Afton, VA United States"
  },
  {
    "BreweryName": "Mountain Island Brew Project",
    "Location": "United States"
  },
  {
    "BreweryName": "Mountain King Brewing Company",
    "Location": "Windham, NY United States"
  },
  {
    "BreweryName": "Mountain Lakes Brewing Company",
    "Location": "Spokane, WA United States"
  },
  {
    "BreweryName": "Mountain Laurel Brewery",
    "Location": "United States"
  },
  {
    "BreweryName": "Mountain Layers Brewing Co.",
    "Location": "Bryson City, NC United States"
  },
  {
    "BreweryName": "Mountain Life Brewing",
    "Location": "United States"
  },
  {
    "BreweryName": "Mountain Lion & A Deer Brewing",
    "Location": "United States"
  },
  {
    "BreweryName": "Mountain Mac Cider Company",
    "Location": "Middlebury, VT United States"
  },
  {
    "BreweryName": "Mountain Madness",
    "Location": "Matten bei Interlaken, Bern Switzerland"
  },
  {
    "BreweryName": "Mountain Magic",
    "Location": "United States"
  },
  {
    "BreweryName": "Mountain Man Brewery",
    "Location": "United States"
  },
  {
    "BreweryName": "Mountain Man Brewing Company",
    "Location": null
  },
  {
    "BreweryName": "Mountain Man Brewing Ltd.",
    "Location": "Reananerree, County Cork Ireland"
  },
  {
    "BreweryName": "Mountain Man Brews",
    "Location": null
  },
  {
    "BreweryName": "Mountain Man Hops",
    "Location": "United States"
  },
  {
    "BreweryName": "Mountain Mashers",
    "Location": "United States"
  },
  {
    "BreweryName": "Mountain Mead",
    "Location": "Wales"
  },
  {
    "BreweryName": "Mountain Meadow Brewery",
    "Location": "United States"
  }
]
