[
  {
    "BreweryName": "Knappstein Enterprise Winery & Brewery",
    "Location": "Clare, South Australia Australia"
  },
  {
    "BreweryName": "Knapptronix Brewing Company",
    "Location": "Lafayette, IN United States"
  },
  {
    "BreweryName": "Knarr Brewing",
    "Location": "United States"
  },
  {
    "BreweryName": "Knärzje GmbH",
    "Location": "Frankfurt, Hessen Germany"
  },
  {
    "BreweryName": "Knaus House Brewery",
    "Location": "United States"
  },
  {
    "BreweryName": "Knee Bone's Brewery",
    "Location": "United States"
  },
  {
    "BreweryName": "Knee Deep Brewing Company",
    "Location": "Auburn, CA United States"
  },
  {
    "BreweryName": "Kneipp Brauerei",
    "Location": "United States"
  },
  {
    "BreweryName": "Knickerbocker Brewing Company",
    "Location": "United States"
  },
  {
    "BreweryName": "KnickerBraü",
    "Location": "United States"
  },
  {
    "BreweryName": "Knickmeyer Brewing",
    "Location": "Carrollton, TX United States"
  },
  {
    "BreweryName": "Kniepmann Home Brew",
    "Location": "United States"
  },
  {
    "BreweryName": "Knife and Plate Brewing Co",
    "Location": "Elgin, IL United States"
  },
  {
    "BreweryName": "Knight And Day Brewing Co.",
    "Location": "United States"
  },
  {
    "BreweryName": "Knightberg",
    "Location": "Saint Petersburg, Санкт-Петербург Russia"
  },
  {
    "BreweryName": "Knights Keep Brewing",
    "Location": "Hamilton, NJ United States"
  },
  {
    "BreweryName": "K-Ninety2 Brewery",
    "Location": "Sweden"
  },
  {
    "BreweryName": "Knittelbräu",
    "Location": "Germany"
  },
  {
    "BreweryName": "Knobby Conch Brewing",
    "Location": "United States"
  },
  {
    "BreweryName": "Knobel Bräu",
    "Location": "Germany"
  },
  {
    "BreweryName": "Knock N' Wolff",
    "Location": "United States"
  },
  {
    "BreweryName": "Knock Out Brewery",
    "Location": "Chile"
  },
  {
    "BreweryName": "Knolled Wood",
    "Location": "United States"
  },
  {
    "BreweryName": "Knölsch",
    "Location": "Germany"
  },
  {
    "BreweryName": "Knolwei",
    "Location": "Netherlands"
  }
]
