[
  {
    "BID": 40193,
    "BeerName": "Amaranto",
    "BeerStyle": "Pale Ale - English",
    "BreweryName": "Zimella",
    "Origin": "Raggio, Emilia-Romagna Italy",
    "BeerAbv": 5.80,
    "BeerIbu": 0.00,
    "BeerLabel": "https://assets.untappd.com/site/beer_logos/beer-_40193_90b5d05658a30b7db35649e7edd4.jpeg",
    "HallRating": 9.15,
    "BAR": 3.35,
    "StylePlus": "96",
    "RatingScore": 3.30,
    "AdjustedRating": "2.1196329935866354079709674033"
  },
  {
    "BID": 2501870,
    "BeerName": "Birra Baracca",
    "BeerStyle": "Lager - Pale",
    "BreweryName": "Cester Camillo",
    "Origin": "Nervesa della Battaglia, Veneto Italy",
    "BeerAbv": 4.80,
    "BeerIbu": 0.00,
    "BeerLabel": "https://assets.untappd.com/site/brewery_logos/brewery-311065_f082c.jpeg",
    "HallRating": 9.15,
    "BAR": 4.10,
    "StylePlus": "108",
    "RatingScore": 3.42,
    "AdjustedRating": "2.1202710541633669673660780086"
  },
  {
    "BID": 6003996,
    "BeerName": "The Likely Light Lager",
    "BeerStyle": "Lager - American Light",
    "BreweryName": "Swamp Head Brewery",
    "Origin": "Gainesville, FL United States",
    "BeerAbv": 4.50,
    "BeerIbu": 0.00,
    "BeerLabel": "https://assets.untappd.com/site/brewery_logos/brewery-SwampHeadBrewery_3070.jpeg",
    "HallRating": 9.15,
    "BAR": 4.11,
    "StylePlus": "101",
    "RatingScore": 3.43,
    "AdjustedRating": "2.1202880896945229982113057468"
  },
  {
    "BID": 6204751,
    "BeerName": "4 Seasons Springbreak",
    "BeerStyle": "IPA - Session",
    "BreweryName": "Het Brouwdok",
    "Origin": "Harlingen, Fryslân Netherlands",
    "BeerAbv": 4.00,
    "BeerIbu": 0.00,
    "BeerLabel": "https://assets.untappd.com/site/brewery_logos/brewery-203287_9274f.jpeg",
    "HallRating": 9.15,
    "BAR": 4.10,
    "StylePlus": "97",
    "RatingScore": 3.49,
    "AdjustedRating": "2.1203181709169398033415940523"
  },
  {
    "BID": 3202339,
    "BeerName": "Marx Städter Himbeer Radler",
    "BeerStyle": "Shandy / Radler",
    "BreweryName": "MARX Chemnitzer Bier",
    "Origin": "Chemnitz, Sachsen Germany",
    "BeerAbv": 2.90,
    "BeerIbu": 0.00,
    "BeerLabel": "https://assets.untappd.com/site/brewery_logos/brewery-386627_f0bfb.jpeg",
    "HallRating": 9.15,
    "BAR": 4.11,
    "StylePlus": "77",
    "RatingScore": 2.61,
    "AdjustedRating": "2.1196887014696808072127527224"
  },
  {
    "BID": 3422611,
    "BeerName": "Pszeniczne",
    "BeerStyle": "Wheat Beer - Hefeweizen",
    "BreweryName": "Browar Minister",
    "Origin": "Poland",
    "BeerAbv": 5.00,
    "BeerIbu": 0.00,
    "BeerLabel": "https://assets.untappd.com/site/beer_logos/beer-3422611_7b5ac_sm.jpeg",
    "HallRating": 9.15,
    "BAR": 4.07,
    "StylePlus": "98",
    "RatingScore": 3.43,
    "AdjustedRating": "2.1202390094859309927874946599"
  },
  {
    "BID": 5215690,
    "BeerName": "Canadian Lager",
    "BeerStyle": "Lager - American Light",
    "BreweryName": "Molson Coors (UK)",
    "Origin": "Burton-on-Trent, Staffordshire England",
    "BeerAbv": 4.00,
    "BeerIbu": 0.00,
    "BeerLabel": "https://assets.untappd.com/site/beer_logos/beer-5215664_0f950_sm.jpeg",
    "HallRating": 9.15,
    "BAR": 3.38,
    "StylePlus": "84",
    "RatingScore": 2.85,
    "AdjustedRating": "2.1195274014201201178684701842"
  },
  {
    "BID": 6407984,
    "BeerName": "Tombhead Helles Lager Halloween Series #6",
    "BeerStyle": "Lager - Helles",
    "BreweryName": "Wittorfer Brauerei Neumünster",
    "Origin": "Neumünster, Schleswig-Holstein Germany",
    "BeerAbv": 5.00,
    "BeerIbu": 0.00,
    "BeerLabel": "https://assets.untappd.com/site/beer_logos/beer-6407984_36650_sm.jpeg",
    "HallRating": 9.15,
    "BAR": 4.10,
    "StylePlus": "89",
    "RatingScore": 3.08,
    "AdjustedRating": "2.1200207850867002925401024765"
  },
  {
    "BID": 3337088,
    "BeerName": "Small Batch West Coast Swag",
    "BeerStyle": "IPA - Session",
    "BreweryName": "Sun King Brewery",
    "Origin": "Indianapolis, IN United States",
    "BeerAbv": 3.10,
    "BeerIbu": 30.00,
    "BeerLabel": "https://assets.untappd.com/site/brewery_logos/brewery-2778_60c22.jpeg",
    "HallRating": 9.15,
    "BAR": 3.37,
    "StylePlus": "97",
    "RatingScore": 3.47,
    "AdjustedRating": "2.1196864573049574486697241974"
  },
  {
    "BID": 1550455,
    "BeerName": "Lansdowne Logger (Ottawa)",
    "BeerStyle": "Lager - Pale",
    "BreweryName": "Craft Beer Market",
    "Origin": "Calgary, AB Canada",
    "BeerAbv": 0.00,
    "BeerIbu": 0.00,
    "BeerLabel": "https://assets.untappd.com/site/brewery_logos/brewery-95001_72c4f.jpeg",
    "HallRating": 9.15,
    "BAR": 4.07,
    "StylePlus": "105",
    "RatingScore": 3.30,
    "AdjustedRating": "2.1201519943639170776310464227"
  },
  {
    "BID": 6005339,
    "BeerName": "Cronus German Wheat",
    "BeerStyle": "Wheat Beer - Hefeweizen",
    "BreweryName": "Privatbrauerei Eichbaum",
    "Origin": "Mannheim, Baden-Württemberg Germany",
    "BeerAbv": 5.30,
    "BeerIbu": 0.00,
    "BeerLabel": "https://assets.untappd.com/site/brewery_logos/brewery-1882_6a0d5.jpeg",
    "HallRating": 9.15,
    "BAR": 4.06,
    "StylePlus": "79",
    "RatingScore": 2.78,
    "AdjustedRating": "2.1197825983766079650638439265"
  },
  {
    "BID": 6604796,
    "BeerName": "Yebisu Sumifukashi (澄深し すみふかし) Creative Brew #11",
    "BeerStyle": "Pilsner - German",
    "BreweryName": "Sapporo Breweries",
    "Origin": "Shibuya-ku, Tokyo Japan",
    "BeerAbv": 5.00,
    "BeerIbu": 0.00,
    "BeerLabel": "https://assets.untappd.com/site/beer_logos/beer-6602858_3b510_sm.jpeg",
    "HallRating": 9.15,
    "BAR": 3.37,
    "StylePlus": "98",
    "RatingScore": 3.40,
    "AdjustedRating": "2.1196680871271291286037415179"
  },
  {
    "BID": 2812471,
    "BeerName": "First Base",
    "BeerStyle": "Lager - Helles",
    "BreweryName": "Volta Bräu",
    "Origin": "Basel, Basel-Stadt Switzerland",
    "BeerAbv": 4.80,
    "BeerIbu": 16.00,
    "BeerLabel": "https://assets.untappd.com/site/beer_logos/beer-2812471_e5f22_sm.jpeg",
    "HallRating": 9.15,
    "BAR": 4.10,
    "StylePlus": "99",
    "RatingScore": 3.44,
    "AdjustedRating": "2.120285493730779511802722533"
  },
  {
    "BID": 1672799,
    "BeerName": "Sandman Wheat",
    "BeerStyle": "Wheat Beer - American Pale Wheat",
    "BreweryName": "Seabright Social",
    "Origin": "Santa Cruz, CA United States",
    "BeerAbv": 5.60,
    "BeerIbu": 19.00,
    "BeerLabel": "https://assets.untappd.com/site/beer_logos/beer-1672799_16bca_sm.jpeg",
    "HallRating": 9.15,
    "BAR": 3.38,
    "StylePlus": "94",
    "RatingScore": 3.32,
    "AdjustedRating": "2.1196530927976766215037477475"
  },
  {
    "BID": 503557,
    "BeerName": "Winterfestbier",
    "BeerStyle": "Festbier",
    "BreweryName": "Landshuter Brauhaus",
    "Origin": "Landshut, Bayern Germany",
    "BeerAbv": 5.60,
    "BeerIbu": 0.00,
    "BeerLabel": "https://assets.untappd.com/site/beer_logos/beer-503557_69eac_sm.jpeg",
    "HallRating": 9.15,
    "BAR": 4.09,
    "StylePlus": "93",
    "RatingScore": 3.41,
    "AdjustedRating": "2.1202541682696871736708253599"
  },
  {
    "BID": 1674974,
    "BeerName": "Crno",
    "BeerStyle": "Lager - Dark",
    "BreweryName": "Brauhaus Braubruder",
    "Origin": "Novi Sad, Војводина Serbia",
    "BeerAbv": 5.00,
    "BeerIbu": 0.00,
    "BeerLabel": "https://assets.untappd.com/site/brewery_logos/brewery-190176_a5ece.jpeg",
    "HallRating": 9.15,
    "BAR": 3.36,
    "StylePlus": "85",
    "RatingScore": 3.01,
    "AdjustedRating": "2.11956351348649351168696139"
  },
  {
    "BID": 3339706,
    "BeerName": "General Nelson",
    "BeerStyle": "Wheat Beer - American Pale Wheat",
    "BreweryName": "Brasserie La Bouquine",
    "Origin": "Courlandon, Grand Est France",
    "BeerAbv": 5.50,
    "BeerIbu": 0.00,
    "BeerLabel": "https://assets.untappd.com/site/brewery_logos/brewery-88367_3e30e.jpeg",
    "HallRating": 9.15,
    "BAR": 4.09,
    "StylePlus": "92",
    "RatingScore": 3.26,
    "AdjustedRating": "2.1201441472950522752538816094"
  },
  {
    "BID": 1674425,
    "BeerName": "Fountain Dale",
    "BeerStyle": "Pale Ale - English",
    "BreweryName": "Lincoln Green",
    "Origin": "Nottingham, Nottinghamshire England",
    "BeerAbv": 4.30,
    "BeerIbu": 35.00,
    "BeerLabel": "https://assets.untappd.com/site/beer_logos/beer-1674425_b72d6_sm.jpeg",
    "HallRating": 9.15,
    "BAR": 4.09,
    "StylePlus": "99",
    "RatingScore": 3.42,
    "AdjustedRating": "2.120258066127883882733552344"
  },
  {
    "BID": 6005116,
    "BeerName": "Wilde Cherry",
    "BeerStyle": "Cider - Sweet",
    "BreweryName": "Sandford Orchards",
    "Origin": "Crediton, Devon England",
    "BeerAbv": 3.40,
    "BeerIbu": 0.00,
    "BeerLabel": "https://assets.untappd.com/site/beer_logos/beer-5022663_08e3e_sm.jpeg",
    "HallRating": 9.15,
    "BAR": 4.07,
    "StylePlus": "95",
    "RatingScore": 3.48,
    "AdjustedRating": "2.1202668165636125163949784523"
  },
  {
    "BID": 1675176,
    "BeerName": "Sheephouse",
    "BeerStyle": "Pale Ale - English",
    "BreweryName": "Northern Monkey Brew Co",
    "Origin": "Bolton, Greater Manchester England",
    "BeerAbv": 4.20,
    "BeerIbu": 0.00,
    "BeerLabel": "https://assets.untappd.com/site/beer_logos/beer-1675176_9311d_sm.jpeg",
    "HallRating": 9.15,
    "BAR": 4.11,
    "StylePlus": "98",
    "RatingScore": 3.38,
    "AdjustedRating": "2.1202547633858198869328217081"
  },
  {
    "BID": 3014585,
    "BeerName": "Hirscherl Helles",
    "BeerStyle": "Lager - Helles",
    "BreweryName": "Roth Bier",
    "Origin": "Schweinfurt, Bayern Germany",
    "BeerAbv": 4.80,
    "BeerIbu": 0.00,
    "BeerLabel": "https://assets.untappd.com/site/beer_logos/beer-3014585_1f632_sm.jpeg",
    "HallRating": 9.15,
    "BAR": 3.39,
    "StylePlus": "100",
    "RatingScore": 3.48,
    "AdjustedRating": "2.1196992811940775990482569706"
  },
  {
    "BID": 1676753,
    "BeerName": "Plzen Waiting For Label",
    "BeerStyle": "Pilsner - Other",
    "BreweryName": "Naparbier",
    "Origin": "Noáin, Navarra Spain",
    "BeerAbv": 5.50,
    "BeerIbu": 0.00,
    "BeerLabel": "https://assets.untappd.com/site/beer_logos/beer-1518683_9f189_sm.jpeg",
    "HallRating": 9.15,
    "BAR": 4.10,
    "StylePlus": "100",
    "RatingScore": 3.43,
    "AdjustedRating": "2.1202717300337008196618925921"
  },
  {
    "BID": 6616375,
    "BeerName": "Czech Mex",
    "BeerStyle": "Lager - Vienna",
    "BreweryName": "Stestí Brewing Company",
    "Origin": "Lovelady, TX United States",
    "BeerAbv": 6.10,
    "BeerIbu": 0.00,
    "BeerLabel": "https://assets.untappd.com/site/brewery_logos/brewery-249774_7cbde.jpeg",
    "HallRating": 9.15,
    "BAR": 4.07,
    "StylePlus": "97",
    "RatingScore": 3.42,
    "AdjustedRating": "2.1202255949035038411092373993"
  },
  {
    "BID": 1676485,
    "BeerName": "Gambrinus Radler",
    "BeerStyle": "Shandy / Radler",
    "BreweryName": "Ottakringer Brauerei",
    "Origin": "Wien, Austria",
    "BeerAbv": 2.50,
    "BeerIbu": 10.00,
    "BeerLabel": "https://assets.untappd.com/site/beer_logos/beer-687010_095e0_sm.jpeg",
    "HallRating": 9.15,
    "BAR": 4.11,
    "StylePlus": "83",
    "RatingScore": 2.82,
    "AdjustedRating": "2.1198431145263957311162851119"
  },
  {
    "BID": 3014849,
    "BeerName": "Three Dollar Bill",
    "BeerStyle": "Pilsner - Other",
    "BreweryName": "SquareHead Brewing Co",
    "Origin": "Holbrook, NY United States",
    "BeerAbv": 5.30,
    "BeerIbu": 0.00,
    "BeerLabel": "https://assets.untappd.com/site/brewery_logos/brewery-149526_677bc.jpeg",
    "HallRating": 9.15,
    "BAR": 4.08,
    "StylePlus": "99",
    "RatingScore": 3.42,
    "AdjustedRating": "2.1202418307184970520635555111"
  }
]
