[
  {
    "BID": 2601995,
    "BeerName": "MiG21",
    "BeerStyle": "Bitter - Extra Special / Strong (ESB)",
    "BreweryName": "Ybnstoker Brauerei",
    "Origin": "Eibenstock, Sachsen Germany",
    "BeerAbv": 5.30,
    "BeerIbu": 40.00,
    "BeerLabel": "https://assets.untappd.com/site/beer_logos/beer-2601995_bf63b_sm.jpeg",
    "HallRating": 0.00,
    "BAR": 0.00,
    "StylePlus": "93",
    "RatingScore": 3.34,
    "AdjustedRating": "2.1218961086912050134466947076"
  },
  {
    "BID": 3610538,
    "BeerName": "Pirate",
    "BeerStyle": "Bitter - Session / Ordinary",
    "BreweryName": "Twisted Brewing Co",
    "Origin": "Westbury, Wiltshire England",
    "BeerAbv": 4.20,
    "BeerIbu": 0.00,
    "BeerLabel": "https://assets.untappd.com/site/beer_logos/beer-1054436_bc8c9_sm.jpeg",
    "HallRating": 0.00,
    "BAR": 0.00,
    "StylePlus": "99",
    "RatingScore": 3.40,
    "AdjustedRating": "2.1216809113254395049097283741"
  },
  {
    "BID": 4031726,
    "BeerName": "Triple",
    "BeerStyle": "Belgian Tripel",
    "BreweryName": "La Brasserie 744",
    "Origin": "La Tour, Auvergne-Rhône-Alpes France",
    "BeerAbv": 7.40,
    "BeerIbu": 0.00,
    "BeerLabel": "https://assets.untappd.com/site/brewery_logos/brewery-359680_2a5cf.jpeg",
    "HallRating": 0.00,
    "BAR": 0.00,
    "StylePlus": "90",
    "RatingScore": 3.29,
    "AdjustedRating": "2.119747439658921083015529487"
  },
  {
    "BID": 17898,
    "BeerName": "Chapeau Faro",
    "BeerStyle": "Lambic - Faro",
    "BreweryName": "Brouwerij De Troch",
    "Origin": "Ternat, Vlaams Gewest Belgium",
    "BeerAbv": 4.75,
    "BeerIbu": 0.00,
    "BeerLabel": "https://assets.untappd.com/site/beer_logos/beer-17898_e8a8c_sm.jpeg",
    "HallRating": 0.00,
    "BAR": 0.00,
    "StylePlus": "97",
    "RatingScore": 3.34,
    "AdjustedRating": "2.123595497780280118185758915"
  },
  {
    "BID": 3823153,
    "BeerName": "Plankstettener Dinkel",
    "BeerStyle": "Specialty Grain",
    "BreweryName": "Riedenburger Brauhaus",
    "Origin": "Riedenburg, Bayern Germany",
    "BeerAbv": 4.90,
    "BeerIbu": 0.00,
    "BeerLabel": "https://assets.untappd.com/site/beer_logos/beer-84410_aeffe_sm.jpeg",
    "HallRating": 0.00,
    "BAR": 0.00,
    "StylePlus": "90",
    "RatingScore": 3.13,
    "AdjustedRating": "2.1274153388306776613553227106"
  },
  {
    "BID": 3333352,
    "BeerName": "Razzle Weisse",
    "BeerStyle": "Sour - Berliner Weisse",
    "BreweryName": "Mazama Brewing",
    "Origin": "Hillsboro, OR United States",
    "BeerAbv": 4.50,
    "BeerIbu": 13.00,
    "BeerLabel": "https://assets.untappd.com/site/brewery_logos/brewery-73223_21ea6.jpeg",
    "HallRating": 0.00,
    "BAR": 0.00,
    "StylePlus": "92",
    "RatingScore": 3.43,
    "AdjustedRating": "2.1197905732993452291697905733"
  },
  {
    "BID": 6501018,
    "BeerName": "Affligem Dubbel",
    "BeerStyle": "Belgian Dubbel",
    "BreweryName": "Affligem Brouwerij",
    "Origin": "Opwijk, Vlaams Gewest Belgium",
    "BeerAbv": 6.80,
    "BeerIbu": 21.00,
    "BeerLabel": "https://assets.untappd.com/site/beer_logos/beer-3566_19b5b_sm.jpeg",
    "HallRating": 0.00,
    "BAR": 0.00,
    "StylePlus": "95",
    "RatingScore": 3.44,
    "AdjustedRating": "2.4532836738086477056440390826"
  },
  {
    "BID": 3504286,
    "BeerName": "Vévoda",
    "BeerStyle": "Pilsner - Czech / Bohemian",
    "BreweryName": "Pivovary Lobkowicz",
    "Origin": "Hlavní město Praha, Czech Republic",
    "BeerAbv": 4.50,
    "BeerIbu": 0.00,
    "BeerLabel": "https://assets.untappd.com/site/beer_logos/beer-80238_c63c1_sm.jpeg",
    "HallRating": 0.00,
    "BAR": 0.00,
    "StylePlus": "87",
    "RatingScore": 3.02,
    "AdjustedRating": "2.1287789432020581832574708094"
  },
  {
    "BID": 2602424,
    "BeerName": "Witte Gij T",
    "BeerStyle": "Wheat Beer - Witbier / Blanche",
    "BreweryName": "Brouwerij St. Joris",
    "Origin": "Breda, Noord-Brabant Netherlands",
    "BeerAbv": 0.00,
    "BeerIbu": 0.00,
    "BeerLabel": "https://assets.untappd.com/site/brewery_logos/brewery-276108_b24a6.jpeg",
    "HallRating": 0.00,
    "BAR": 0.00,
    "StylePlus": "93",
    "RatingScore": 3.25,
    "AdjustedRating": "2.1195948192045349456251421544"
  },
  {
    "BID": 3610552,
    "BeerName": "Nia Domo Proost!",
    "BeerStyle": "Belgian Blonde",
    "BreweryName": "Nia Domo",
    "Origin": "Netherlands",
    "BeerAbv": 7.50,
    "BeerIbu": 0.00,
    "BeerLabel": "https://assets.untappd.com/site/assets/images/temp/badge-beer-default.png",
    "HallRating": 0.00,
    "BAR": 0.00,
    "StylePlus": "98",
    "RatingScore": 3.45,
    "AdjustedRating": "2.1194351187782946821621324347"
  },
  {
    "BID": 4031768,
    "BeerName": "Zombeer",
    "BeerStyle": "Pumpkin / Yam Beer",
    "BreweryName": "Brasserie de Mai",
    "Origin": "Carvin, Hauts-de-France France",
    "BeerAbv": 6.50,
    "BeerIbu": 0.00,
    "BeerLabel": "https://assets.untappd.com/site/beer_logos/beer-4031768_7b8d9_sm.jpeg",
    "HallRating": 0.00,
    "BAR": 0.00,
    "StylePlus": "91",
    "RatingScore": 3.35,
    "AdjustedRating": "2.1194027593413378730722983428"
  },
  {
    "BID": 17929,
    "BeerName": "Blue Pig Tavern Ale",
    "BeerStyle": "Pale Ale - American",
    "BreweryName": "Flying Fish Brewing Co.",
    "Origin": "Baltimore, MD United States",
    "BeerAbv": 5.20,
    "BeerIbu": 11.00,
    "BeerLabel": "https://assets.untappd.com/site/brewery_logos/brewery-541_ad18b.jpeg",
    "HallRating": 0.00,
    "BAR": 0.00,
    "StylePlus": "96",
    "RatingScore": 3.47,
    "AdjustedRating": "2.1252120851576481833184401206"
  },
  {
    "BID": 3822985,
    "BeerName": "Ale Best Bitter 12",
    "BeerStyle": "Bitter - Best",
    "BreweryName": "Pivovarský dvůr Zvíkov",
    "Origin": "Zvíkovské Podhradí, Jihočeský kraj Czech Republic",
    "BeerAbv": 5.20,
    "BeerIbu": 0.00,
    "BeerLabel": "https://assets.untappd.com/site/brewery_logos/brewery-32813_90bbe.jpeg",
    "HallRating": 0.00,
    "BAR": 0.00,
    "StylePlus": "94",
    "RatingScore": 3.33,
    "AdjustedRating": "2.1202332762092241280246216569"
  },
  {
    "BID": 3309,
    "BeerName": "Trippleberry Wheat",
    "BeerStyle": "Wheat Beer - Fruited",
    "BreweryName": "Barley Brothers Restaurant & Brewery",
    "Origin": "Lake Havasu City, AZ United States",
    "BeerAbv": 6.70,
    "BeerIbu": 0.00,
    "BeerLabel": "https://assets.untappd.com/site/beer_logos/beer-TripppleberryWheat_3309.jpeg",
    "HallRating": 0.00,
    "BAR": 0.00,
    "StylePlus": "96",
    "RatingScore": 3.46,
    "AdjustedRating": "2.1230687229194401647395529495"
  },
  {
    "BID": 6500945,
    "BeerName": "Watermelon Vodka Seltzer",
    "BeerStyle": "RTD - Vodka Seltzer",
    "BreweryName": "High Noon",
    "Origin": "Modesto, CA United States",
    "BeerAbv": 4.50,
    "BeerIbu": 0.00,
    "BeerLabel": "https://assets.untappd.com/site/beer_logos/beer-6473892_edd6c_sm.jpeg",
    "HallRating": 0.00,
    "BAR": 0.00,
    "StylePlus": "96",
    "RatingScore": 3.32,
    "AdjustedRating": "2.1196530927976766215037477475"
  },
  {
    "BID": 3504420,
    "BeerName": "Rose & Crown Best Bitter",
    "BeerStyle": "Bitter - Session / Ordinary",
    "BreweryName": "Greene King House Brewery",
    "Origin": "England",
    "BeerAbv": 3.90,
    "BeerIbu": 0.00,
    "BeerLabel": "https://assets.untappd.com/site/brewery_logos/brewery-431711_d7a95.jpeg",
    "HallRating": 0.00,
    "BAR": 0.00,
    "StylePlus": "93",
    "RatingScore": 3.17,
    "AdjustedRating": "2.1194186729594808428304664865"
  },
  {
    "BID": 2602434,
    "BeerName": "Roestig Blond",
    "BeerStyle": "Belgian Blonde",
    "BreweryName": "Brouwerij Scheveningen",
    "Origin": "Den Haag, Zuid-Holland Netherlands",
    "BeerAbv": 6.00,
    "BeerIbu": 0.00,
    "BeerLabel": "https://assets.untappd.com/site/beer_logos/beer-2600794_dbd56_sm.jpeg",
    "HallRating": 0.00,
    "BAR": 0.00,
    "StylePlus": "98",
    "RatingScore": 3.43,
    "AdjustedRating": "2.1248950100197906423868261535"
  },
  {
    "BID": 3610566,
    "BeerName": "Belgian Pale Ale",
    "BeerStyle": "Pale Ale - Belgian",
    "BreweryName": "Hey Joe Brewing Company",
    "Origin": "Franschhoek, Western Cape South Africa",
    "BeerAbv": 5.00,
    "BeerIbu": 22.00,
    "BeerLabel": "https://assets.untappd.com/site/beer_logos/beer-3610566_d6f98_sm.jpeg",
    "HallRating": 0.00,
    "BAR": 0.00,
    "StylePlus": "99",
    "RatingScore": 3.49,
    "AdjustedRating": "2.1208414972492826658608883706"
  },
  {
    "BID": 4031923,
    "BeerName": "Nissenatt",
    "BeerStyle": "Winter Warmer",
    "BreweryName": "Lindesnes Brygghus",
    "Origin": "Spangereid, Agder Norway",
    "BeerAbv": 4.70,
    "BeerIbu": 0.00,
    "BeerLabel": "https://assets.untappd.com/site/beer_logos/beer-4031923_98180_sm.jpeg",
    "HallRating": 0.00,
    "BAR": 0.00,
    "StylePlus": "85",
    "RatingScore": 3.10,
    "AdjustedRating": "2.125130039092497371880739303"
  },
  {
    "BID": 1796,
    "BeerName": "Us Heit Dubbel Tarwe Bier",
    "BeerStyle": "Wheat Beer - Other",
    "BreweryName": "De Friese Bierbrouwerij",
    "Origin": "Bolsward, Fryslân Netherlands",
    "BeerAbv": 8.00,
    "BeerIbu": 35.00,
    "BeerLabel": "https://assets.untappd.com/site/beer_logos/beer-UsHeitDubbelTarweBier_1796.jpeg",
    "HallRating": 0.00,
    "BAR": 0.00,
    "StylePlus": "95",
    "RatingScore": 3.39,
    "AdjustedRating": "2.1312585750018574011243468139"
  },
  {
    "BID": 3623590,
    "BeerName": "Diesel",
    "BeerStyle": "Stout - English",
    "BreweryName": "Maximus Brouwerij",
    "Origin": "Utrecht, Netherlands",
    "BeerAbv": 6.00,
    "BeerIbu": 35.00,
    "BeerLabel": "https://assets.untappd.com/site/beer_logos/beer-3184892_99ec3_sm.jpeg",
    "HallRating": 0.00,
    "BAR": 0.00,
    "StylePlus": "91",
    "RatingScore": 3.31,
    "AdjustedRating": "2.150409037787300350603817686"
  },
  {
    "BID": 33112,
    "BeerName": "La Vlimeuse",
    "BeerStyle": "Red Ale - American Amber / Red",
    "BreweryName": "Microbrasserie Saint-Arnould",
    "Origin": "Mont-Tremblant, QC Canada",
    "BeerAbv": 6.20,
    "BeerIbu": 28.00,
    "BeerLabel": "https://assets.untappd.com/site/beer_logos/beer-33112_f74b7_sm.jpeg",
    "HallRating": 0.00,
    "BAR": 0.00,
    "StylePlus": "97",
    "RatingScore": 3.43,
    "AdjustedRating": "2.1233010979150829355831661329"
  },
  {
    "BID": 6500948,
    "BeerName": "Polar Beer",
    "BeerStyle": "Blonde / Golden Ale - American",
    "BreweryName": "Little Critters Brewing Company",
    "Origin": "Sheffield, South Yorkshire England",
    "BeerAbv": 4.20,
    "BeerIbu": 0.00,
    "BeerLabel": "https://assets.untappd.com/site/beer_logos/beer-6500948_fcb72_sm.jpeg",
    "HallRating": 0.00,
    "BAR": 0.00,
    "StylePlus": "96",
    "RatingScore": 3.46,
    "AdjustedRating": "2.1200120438877269785583816213"
  },
  {
    "BID": 3504431,
    "BeerName": "Brewing After Sex Is Very Relaxing.",
    "BeerStyle": "Farmhouse Ale - Saison",
    "BreweryName": "MONYO Brewing Co.",
    "Origin": "Hungary",
    "BeerAbv": 6.30,
    "BeerIbu": 15.00,
    "BeerLabel": "https://assets.untappd.com/site/beer_logos/beer-2999376_65866_sm.jpeg",
    "HallRating": 0.00,
    "BAR": 0.00,
    "StylePlus": "93",
    "RatingScore": 3.43,
    "AdjustedRating": "2.1212917905436608678503940349"
  },
  {
    "BID": 2602435,
    "BeerName": "Blue Fin Stout",
    "BeerStyle": "Stout - Irish Dry",
    "BreweryName": "Shipyard Brewing Company",
    "Origin": "Portland, ME United States",
    "BeerAbv": 4.70,
    "BeerIbu": 43.00,
    "BeerLabel": "https://assets.untappd.com/site/beer_logos/beer-14854_a54f5_sm.jpeg",
    "HallRating": 0.00,
    "BAR": 0.00,
    "StylePlus": "93",
    "RatingScore": 3.38,
    "AdjustedRating": "2.1634472443034462792969927986"
  }
]
