[
  {
    "BID": 6412506,
    "BeerName": "Clocktower Sour",
    "BeerStyle": "Sour - Fruited",
    "BreweryName": "Greener Pastures Brewing Company",
    "Origin": "Camden, SC United States",
    "BeerAbv": 4.50,
    "BeerIbu": 6.00,
    "BeerLabel": "https://assets.untappd.com/site/beer_logos/beer-6412506_20267_sm.jpeg",
    "HallRating": 15.41,
    "BAR": 3.14,
    "StylePlus": "109",
    "RatingScore": 4.19,
    "AdjustedRating": "2.0925953832077556509957051933"
  },
  {
    "BID": 6202919,
    "BeerName": "24/7",
    "BeerStyle": "Non-Alcoholic - Lager",
    "BreweryName": "Sonnenbräu",
    "Origin": "Rebstein, Sankt Gallen Switzerland",
    "BeerAbv": 0.00,
    "BeerIbu": 0.00,
    "BeerLabel": "https://assets.untappd.com/site/brewery_logos/brewery-SonnenbrauAG_12918.jpeg",
    "HallRating": 15.41,
    "BAR": 3.14,
    "StylePlus": "104",
    "RatingScore": 2.81,
    "AdjustedRating": "2.0925332860021299041543130559"
  },
  {
    "BID": 5212727,
    "BeerName": "1890 Lager",
    "BeerStyle": "Lager - American",
    "BreweryName": "Barrier Brewing Company",
    "Origin": "Oceanside, NY United States",
    "BeerAbv": 0.00,
    "BeerIbu": 0.00,
    "BeerLabel": "https://assets.untappd.com/site/brewery_logos/brewery-4171_dc08b.jpeg",
    "HallRating": 15.41,
    "BAR": 3.14,
    "StylePlus": "97",
    "RatingScore": 3.37,
    "AdjustedRating": "2.092558484868180931858066387"
  },
  {
    "BID": 6303920,
    "BeerName": "Woodruff Kolsch",
    "BeerStyle": "Kölsch",
    "BreweryName": "Third Eye Brewing Company",
    "Origin": "Cincinnati, OH United States",
    "BeerAbv": 5.00,
    "BeerIbu": 25.00,
    "BeerLabel": "https://assets.untappd.com/site/brewery_logos/brewery-467597_4c8c6.jpeg",
    "HallRating": 15.41,
    "BAR": 3.14,
    "StylePlus": "105",
    "RatingScore": 3.78,
    "AdjustedRating": "2.0925769340379682914268857901"
  },
  {
    "BID": 6412650,
    "BeerName": "GRUNNEGER METWORST WIT",
    "BeerStyle": "Wheat Beer - Other",
    "BreweryName": "Het Brouwdok",
    "Origin": "Harlingen, Fryslân Netherlands",
    "BeerAbv": 5.40,
    "BeerIbu": 16.00,
    "BeerLabel": "https://assets.untappd.com/site/brewery_logos/brewery-203287_9274f.jpeg",
    "HallRating": 15.41,
    "BAR": 3.14,
    "StylePlus": "98",
    "RatingScore": 3.50,
    "AdjustedRating": "2.0925643346049427775750091246"
  },
  {
    "BID": 6202462,
    "BeerName": "Sometimes Always (12/12/24)",
    "BeerStyle": "Farmhouse Ale - Saison",
    "BreweryName": "Casey Brewing & Blending",
    "Origin": "Glenwood Springs, CO United States",
    "BeerAbv": 7.00,
    "BeerIbu": 0.00,
    "BeerLabel": "https://assets.untappd.com/site/brewery_logos/brewery-127424_d63e0.jpeg",
    "HallRating": 15.41,
    "BAR": 3.14,
    "StylePlus": "116",
    "RatingScore": 4.30,
    "AdjustedRating": "2.0926003329850156742946567404"
  },
  {
    "BID": 4961948,
    "BeerName": "Relax (It Will All Be Over Soon)",
    "BeerStyle": "IPA - New England / Hazy",
    "BreweryName": "Bicycle Brewing",
    "Origin": "Copenhagen, Region Hovedstaden Denmark",
    "BeerAbv": 5.40,
    "BeerIbu": 0.00,
    "BeerLabel": "https://assets.untappd.com/site/beer_logos/beer-4961948_098a2_sm.jpeg",
    "HallRating": 15.41,
    "BAR": 3.14,
    "StylePlus": "99",
    "RatingScore": 3.82,
    "AdjustedRating": "2.0925787339569719362628681709"
  },
  {
    "BID": 6303577,
    "BeerName": "Rouge Gorge (2025)",
    "BeerStyle": "Sour - Fruited",
    "BreweryName": "La Source Beer Co.",
    "Origin": "Bruxelles, Belgium",
    "BeerAbv": 5.10,
    "BeerIbu": 0.00,
    "BeerLabel": "https://assets.untappd.com/site/beer_logos/beer-6303577_09645_sm.jpeg",
    "HallRating": 15.41,
    "BAR": 3.14,
    "StylePlus": "103",
    "RatingScore": 3.98,
    "AdjustedRating": "2.0925859336329865156067976941"
  },
  {
    "BID": 6420257,
    "BeerName": "New Growth Spruce",
    "BeerStyle": "Pale Ale - American",
    "BreweryName": "Rusty Gold Brewing",
    "Origin": "Canonsburg, PA United States",
    "BeerAbv": 6.50,
    "BeerIbu": 0.00,
    "BeerLabel": "https://assets.untappd.com/site/brewery_logos/brewery-296965_e1560.jpeg",
    "HallRating": 15.41,
    "BAR": 3.14,
    "StylePlus": "107",
    "RatingScore": 3.85,
    "AdjustedRating": "2.0925800838962246698898549565"
  },
  {
    "BID": 6202570,
    "BeerName": "Maker’s Mark Bourbon whiskey Stout",
    "BeerStyle": "Stout - Imperial / Double Pastry",
    "BreweryName": "Sonthaya brewing",
    "Origin": "Thailand",
    "BeerAbv": 9.60,
    "BeerIbu": 40.00,
    "BeerLabel": "https://assets.untappd.com/site/beer_logos/beer-6202570_5049d_sm.jpeg",
    "HallRating": 15.41,
    "BAR": 3.14,
    "StylePlus": "91",
    "RatingScore": 3.79,
    "AdjustedRating": "2.0925773840177192026358813853"
  },
  {
    "BID": 6618340,
    "BeerName": "Tupps Full Grown Dubai Chocolate",
    "BeerStyle": "Stout - American",
    "BreweryName": "TUPPS Brewery",
    "Origin": "McKinney, TX United States",
    "BeerAbv": 12.10,
    "BeerIbu": 0.00,
    "BeerLabel": "https://assets.untappd.com/site/brewery_logos/brewery-196598_e1d85.jpeg",
    "HallRating": 15.41,
    "BAR": 3.14,
    "StylePlus": "106",
    "RatingScore": 3.98,
    "AdjustedRating": "2.0925859336329865156067976941"
  },
  {
    "BID": 6407034,
    "BeerName": "雙獅 Double Lions",
    "BeerStyle": "IPA - Imperial / Double",
    "BreweryName": "Black Drongo Brewing Co. 烏鶖啤酒",
    "Origin": "Taiwan",
    "BeerAbv": 9.50,
    "BeerIbu": 0.00,
    "BeerLabel": "https://assets.untappd.com/site/brewery_logos/brewery-432049_599fc.jpeg",
    "HallRating": 15.41,
    "BAR": 3.14,
    "StylePlus": "106",
    "RatingScore": 4.09,
    "AdjustedRating": "2.0925908834102465389057492413"
  },
  {
    "BID": 6420369,
    "BeerName": "Forty-seven Suns",
    "BeerStyle": "Pale Ale - New England / Hazy",
    "BreweryName": "Shrine Brewing",
    "Origin": "San Luis Obispo, CA United States",
    "BeerAbv": 6.00,
    "BeerIbu": 0.00,
    "BeerLabel": "https://assets.untappd.com/site/brewery_logos/brewery-572966_f180f.jpeg",
    "HallRating": 15.41,
    "BAR": 3.14,
    "StylePlus": "107",
    "RatingScore": 4.04,
    "AdjustedRating": "2.0925886335114919828607712653"
  },
  {
    "BID": 6201106,
    "BeerName": "Denizens Hard Cider",
    "BeerStyle": "Cider - Dry",
    "BreweryName": "Denizens Brewing Co.",
    "Origin": "Silver Spring, MD United States",
    "BeerAbv": 6.00,
    "BeerIbu": 0.00,
    "BeerLabel": "https://assets.untappd.com/site/brewery_logos/brewery-140709_6ee03.jpeg",
    "HallRating": 15.41,
    "BAR": 3.14,
    "StylePlus": "101",
    "RatingScore": 3.69,
    "AdjustedRating": "2.0925728842202100905459254334"
  },
  {
    "BID": 4961942,
    "BeerName": "Smith St Pale",
    "BeerStyle": "Pale Ale - American",
    "BreweryName": "Bacchus Brewing Co.",
    "Origin": "Capalaba, Queensland Australia",
    "BeerAbv": 5.00,
    "BeerIbu": 0.00,
    "BeerLabel": "https://assets.untappd.com/site/beer_logos/beer-4961942_e68f9_sm.jpeg",
    "HallRating": 15.41,
    "BAR": 3.14,
    "StylePlus": "101",
    "RatingScore": 3.65,
    "AdjustedRating": "2.0925710843012064457099430526"
  },
  {
    "BID": 6407294,
    "BeerName": "800 Jaar Kampen",
    "BeerStyle": "IPA - New England / Hazy",
    "BreweryName": "Trots Van Kampen",
    "Origin": "Kampen, Overijssel Netherlands",
    "BeerAbv": 6.50,
    "BeerIbu": 35.00,
    "BeerLabel": "https://assets.untappd.com/site/beer_logos/beer-6407294_f3a9e_sm.jpeg",
    "HallRating": 15.41,
    "BAR": 3.14,
    "StylePlus": "92",
    "RatingScore": 3.57,
    "AdjustedRating": "2.092567484463199156037978291"
  },
  {
    "BID": 6420412,
    "BeerName": "Drinkability Brown",
    "BeerStyle": "Brown Ale - Other",
    "BreweryName": "Lucky 7 Beer Co",
    "Origin": "Hay on Wye, Powys Wales",
    "BeerAbv": 3.20,
    "BeerIbu": 0.00,
    "BeerLabel": "https://assets.untappd.com/site/brewery_logos/brewery-167414_e12b8.jpeg",
    "HallRating": 15.41,
    "BAR": 3.14,
    "StylePlus": "106",
    "RatingScore": 3.82,
    "AdjustedRating": "2.0925787339569719362628681709"
  },
  {
    "BID": 6224447,
    "BeerName": "Davis Dream 2025",
    "BeerStyle": "IPA - New England / Hazy",
    "BreweryName": "SirHopper",
    "Origin": "San Martín, Provincia de Buenos Aires Argentina",
    "BeerAbv": 7.00,
    "BeerIbu": 0.00,
    "BeerLabel": "https://assets.untappd.com/site/brewery_logos/brewery-261711_25532.jpeg",
    "HallRating": 15.41,
    "BAR": 3.14,
    "StylePlus": "105",
    "RatingScore": 4.05,
    "AdjustedRating": "2.0925890834912428940697668605"
  },
  {
    "BID": 811990,
    "BeerName": "SuperNova",
    "BeerStyle": "IPA - Other",
    "BreweryName": "Kabinet Brewery",
    "Origin": "Nemenikuće, Grad Beograd Serbia",
    "BeerAbv": 6.80,
    "BeerIbu": 51.00,
    "BeerLabel": "https://assets.untappd.com/site/beer_logos/beer-811990_58a4c_sm.jpeg",
    "HallRating": 15.41,
    "BAR": 9.68,
    "StylePlus": "101",
    "RatingScore": 3.65,
    "AdjustedRating": "2.1210277988430851390187575314"
  },
  {
    "BID": 6407459,
    "BeerName": "Johatsu",
    "BeerStyle": "Sour - Other",
    "BreweryName": "Starfire Brewing",
    "Origin": "Tempe, AZ United States",
    "BeerAbv": 7.00,
    "BeerIbu": 0.00,
    "BeerLabel": "https://assets.untappd.com/site/beer_logos/beer-6407459_e41e7_sm.jpeg",
    "HallRating": 15.41,
    "BAR": 3.14,
    "StylePlus": "117",
    "RatingScore": 4.43,
    "AdjustedRating": "2.092606182721777520011599478"
  },
  {
    "BID": 6420887,
    "BeerName": "Nikolai (Batch No. Two)",
    "BeerStyle": "Farmhouse Ale - Saison",
    "BreweryName": "Fair Isle Brewing",
    "Origin": "Seattle, WA United States",
    "BeerAbv": 4.50,
    "BeerIbu": 0.00,
    "BeerLabel": "https://assets.untappd.com/site/brewery_logos/brewery-455226_9d03f.jpeg",
    "HallRating": 15.41,
    "BAR": 3.14,
    "StylePlus": "114",
    "RatingScore": 4.21,
    "AdjustedRating": "2.0925962831672574734136963837"
  },
  {
    "BID": 6222970,
    "BeerName": "Ramblin Nan Original",
    "BeerStyle": "Cider - Dry",
    "BreweryName": "Pile O' Bones Brewing Company",
    "Origin": "Regina, SK Canada",
    "BeerAbv": 5.00,
    "BeerIbu": 0.00,
    "BeerLabel": "https://assets.untappd.com/site/beer_logos/beer-6222970_d4b2b_sm.jpeg",
    "HallRating": 15.41,
    "BAR": 3.14,
    "StylePlus": "98",
    "RatingScore": 3.58,
    "AdjustedRating": "2.0925679344429500672469738862"
  },
  {
    "BID": 6605779,
    "BeerName": "Gulab Jamun",
    "BeerStyle": "Mead - Metheglin",
    "BreweryName": "Zymarium Meadery",
    "Origin": "Orlando, FL United States",
    "BeerAbv": 14.00,
    "BeerIbu": 0.00,
    "BeerLabel": "https://assets.untappd.com/site/beer_logos/beer-6605779_e48a9_sm.jpeg",
    "HallRating": 15.41,
    "BAR": 3.14,
    "StylePlus": "114",
    "RatingScore": 4.40,
    "AdjustedRating": "2.0926048327825247863846126924"
  },
  {
    "BID": 6407588,
    "BeerName": "Rye’D the Wave",
    "BeerStyle": "IPA - Rye",
    "BreweryName": "Fenton Winery & Brewery",
    "Origin": "Fenton, MI United States",
    "BeerAbv": 9.00,
    "BeerIbu": 56.00,
    "BeerLabel": "https://assets.untappd.com/site/brewery_logos/brewery-FentonWineryBrewery_17655.jpeg",
    "HallRating": 15.41,
    "BAR": 3.14,
    "StylePlus": "99",
    "RatingScore": 3.67,
    "AdjustedRating": "2.092571984260708268127934243"
  },
  {
    "BID": 6418514,
    "BeerName": "Brumosa",
    "BeerStyle": "Pale Ale - New England / Hazy",
    "BreweryName": "Cervecería Insurgente",
    "Origin": "Tijuana, Baja California Mexico",
    "BeerAbv": 5.00,
    "BeerIbu": 0.00,
    "BeerLabel": "https://assets.untappd.com/site/brewery_logos/brewery-CerveceriaInsurgente_12025.jpeg",
    "HallRating": 15.41,
    "BAR": 3.14,
    "StylePlus": "95",
    "RatingScore": 3.60,
    "AdjustedRating": "2.0925688344024518896649650766"
  }
]
