[
  {
    "BID": 4447369,
    "BeerName": "Mango Blanc - Foeder Aged Brett Berliner Weisse",
    "BeerStyle": "Brett Beer",
    "BreweryName": "Imperial Oak Brewing",
    "Origin": "Willow Springs, IL United States",
    "BeerAbv": 4.50,
    "BeerIbu": 0.00,
    "BeerLabel": "https://assets.untappd.com/site/brewery_logos/brewery-129884_0778d.jpeg",
    "HallRating": 13.94,
    "BAR": 4.46,
    "StylePlus": "103",
    "RatingScore": 3.98,
    "AdjustedRating": "2.390114849469781984806970462"
  },
  {
    "BID": 6012394,
    "BeerName": "Tortured Fruit V",
    "BeerStyle": "Sour - Fruited",
    "BreweryName": "Snitz Creek Brewery",
    "Origin": "Lebanon, PA United States",
    "BeerAbv": 7.00,
    "BeerIbu": 5.00,
    "BeerLabel": "https://assets.untappd.com/site/beer_logos/beer-6012394_230a8_sm.jpeg",
    "HallRating": 13.94,
    "BAR": 4.46,
    "StylePlus": "102",
    "RatingScore": 3.89,
    "AdjustedRating": "2.3901011265625253414450831498"
  },
  {
    "BID": 3349212,
    "BeerName": "Barrel Aged Duncan Clan 2018",
    "BeerStyle": "Scotch Ale / Wee Heavy",
    "BreweryName": "Brink Brewing Co",
    "Origin": "Cincinnati, OH United States",
    "BeerAbv": 14.50,
    "BeerIbu": 0.00,
    "BeerLabel": "https://assets.untappd.com/site/beer_logos/beer-3349212_77960_sm.jpeg",
    "HallRating": 13.94,
    "BAR": 4.46,
    "StylePlus": "103",
    "RatingScore": 4.32,
    "AdjustedRating": "2.3901666915638626375074336414"
  },
  {
    "BID": 3349200,
    "BeerName": "Lurdes West Cost IPA",
    "BeerStyle": "IPA - American",
    "BreweryName": "Mental Moon",
    "Origin": "São Paulo, Brazil",
    "BeerAbv": 6.30,
    "BeerIbu": 65.00,
    "BeerLabel": "https://assets.untappd.com/site/beer_logos/beer-3349200_fdeef_sm.jpeg",
    "HallRating": 13.94,
    "BAR": 4.46,
    "StylePlus": "104",
    "RatingScore": 3.76,
    "AdjustedRating": "2.3900813045853768565890236989"
  },
  {
    "BID": 3349713,
    "BeerName": "Slip Scraper",
    "BeerStyle": "Stout - Milk / Sweet",
    "BreweryName": "Lock 32 Brewing Company",
    "Origin": "Pittsford, NY United States",
    "BeerAbv": 5.00,
    "BeerIbu": 31.00,
    "BeerLabel": "https://assets.untappd.com/site/brewery_logos/brewery-116034_54963.jpeg",
    "HallRating": 13.94,
    "BAR": 4.46,
    "StylePlus": "102",
    "RatingScore": 3.69,
    "AdjustedRating": "2.3900706312130661339742224561"
  },
  {
    "BID": 3349780,
    "BeerName": "Cascara Hibiscus",
    "BeerStyle": "Mead - Traditional",
    "BreweryName": "Local Cider & Angry Bear Mead",
    "Origin": "Tulsa, OK United States",
    "BeerAbv": 8.00,
    "BeerIbu": 0.00,
    "BeerLabel": "https://assets.untappd.com/site/brewery_logos/brewery-420614_219b6.jpeg",
    "HallRating": 13.94,
    "BAR": 4.46,
    "StylePlus": "101",
    "RatingScore": 3.65,
    "AdjustedRating": "2.3900645321431742924800503173"
  },
  {
    "BID": 3349770,
    "BeerName": "Das Crispy",
    "BeerStyle": "Lager - Dortmunder / Export",
    "BreweryName": "Device Brewing Company",
    "Origin": "Sacramento, CA United States",
    "BeerAbv": 5.20,
    "BeerIbu": 15.00,
    "BeerLabel": "https://assets.untappd.com/site/beer_logos/beer-3349770_69023_sm.jpeg",
    "HallRating": 13.94,
    "BAR": 4.46,
    "StylePlus": "120",
    "RatingScore": 3.65,
    "AdjustedRating": "2.3900645321431742924800503173"
  },
  {
    "BID": 4007334,
    "BeerName": "Haunted Haze",
    "BeerStyle": "IPA - Imperial / Double New England / Hazy",
    "BreweryName": "Axe & Arrow Brewing",
    "Origin": "Glassboro, NJ United States",
    "BeerAbv": 8.00,
    "BeerIbu": 35.00,
    "BeerLabel": "https://assets.untappd.com/site/beer_logos/beer-4007334_46645_sm.jpeg",
    "HallRating": 13.94,
    "BAR": 6.92,
    "StylePlus": "100",
    "RatingScore": 3.87,
    "AdjustedRating": "2.3920449858551191014804772235"
  },
  {
    "BID": 3348368,
    "BeerName": "Lemon Drop Ale",
    "BeerStyle": "Pale Ale - American",
    "BreweryName": "Lincoln Beer Company",
    "Origin": "Burbank, CA United States",
    "BeerAbv": 6.00,
    "BeerIbu": 0.00,
    "BeerLabel": "https://assets.untappd.com/site/brewery_logos/brewery-309904_f3b34.jpeg",
    "HallRating": 13.93,
    "BAR": 4.48,
    "StylePlus": "110",
    "RatingScore": 3.62,
    "AdjustedRating": "2.3900630322143329049593848204"
  },
  {
    "BID": 4940363,
    "BeerName": "Altar of the Orc Lord Double Barrel Aged In Tiny Horsey Barrels",
    "BeerStyle": "Barleywine - English",
    "BreweryName": "Modern Times Beer",
    "Origin": "San Diego, CA United States",
    "BeerAbv": 12.50,
    "BeerIbu": 0.00,
    "BeerLabel": "https://assets.untappd.com/site/beer_logos/beer-4940363_822cd_sm.jpeg",
    "HallRating": 13.93,
    "BAR": 6.91,
    "StylePlus": "102",
    "RatingScore": 4.45,
    "AdjustedRating": "2.3928706580002907028602347329"
  },
  {
    "BID": 3338807,
    "BeerName": "Phildrove",
    "BeerStyle": "Pale Ale - New England / Hazy",
    "BreweryName": "Various Artists Brewing Company",
    "Origin": "Nashville, TN United States",
    "BeerAbv": 5.40,
    "BeerIbu": 0.00,
    "BeerLabel": "https://assets.untappd.com/site/brewery_logos/brewery-427824_f99a4.jpeg",
    "HallRating": 13.93,
    "BAR": 4.48,
    "StylePlus": "101",
    "RatingScore": 3.91,
    "AdjustedRating": "2.3901079752481626613471447176"
  },
  {
    "BID": 4980585,
    "BeerName": "All About the Amarillo Fresh Hop IPA",
    "BeerStyle": "IPA - American",
    "BreweryName": "Deschutes Brewery",
    "Origin": "Bend, OR United States",
    "BeerAbv": 6.30,
    "BeerIbu": 55.00,
    "BeerLabel": "https://assets.untappd.com/site/beer_logos/beer-4980585_93ffd_sm.jpeg",
    "HallRating": 13.93,
    "BAR": 4.48,
    "StylePlus": "104",
    "RatingScore": 4.01,
    "AdjustedRating": "2.3901234728460349911360274407"
  },
  {
    "BID": 4962088,
    "BeerName": "Spiraling Vines",
    "BeerStyle": "IPA - Imperial / Double New England / Hazy",
    "BreweryName": "Riverlands Brewing Company",
    "Origin": "St Charles, IL United States",
    "BeerAbv": 8.00,
    "BeerIbu": 0.00,
    "BeerLabel": "https://assets.untappd.com/site/beer_logos/beer-4962088_243ff_sm.jpeg",
    "HallRating": 13.93,
    "BAR": 6.89,
    "StylePlus": "100",
    "RatingScore": 4.11,
    "AdjustedRating": "2.3923286619976694592329504059"
  },
  {
    "BID": 3342485,
    "BeerName": "Ceci N'est  Pas Une Gueuze (2016)",
    "BeerStyle": "Lambic - Gueuze",
    "BreweryName": "LTM - Les Trois Mousquetaires Microbrasserie",
    "Origin": "Brossard, QC Canada",
    "BeerAbv": 5.50,
    "BeerIbu": 0.00,
    "BeerLabel": "https://assets.untappd.com/site/brewery_logos/brewery-2546_49837.jpeg",
    "HallRating": 13.93,
    "BAR": 4.48,
    "StylePlus": "104",
    "RatingScore": 3.87,
    "AdjustedRating": "2.3901017762090137294315916283"
  },
  {
    "BID": 6011579,
    "BeerName": "Kelsey Montague (KMA) Blood Orange",
    "BeerStyle": "Wheat Beer - Fruited",
    "BreweryName": "Danico Brewing Company",
    "Origin": "Denver, CO United States",
    "BeerAbv": 5.30,
    "BeerIbu": 0.00,
    "BeerLabel": "https://assets.untappd.com/site/brewery_logos/brewery-533025_c54a8.jpeg",
    "HallRating": 13.93,
    "BAR": 4.48,
    "StylePlus": "111",
    "RatingScore": 3.66,
    "AdjustedRating": "2.3900692312534818368749379096"
  },
  {
    "BID": 3349633,
    "BeerName": "Morning Halp!",
    "BeerStyle": "Stout - Coffee",
    "BreweryName": "Terrestrial Brewing Company",
    "Origin": "Cleveland, OH United States",
    "BeerAbv": 8.00,
    "BeerIbu": 27.00,
    "BeerLabel": "https://assets.untappd.com/site/beer_logos/beer-3051353_d4413_sm.jpeg",
    "HallRating": 13.93,
    "BAR": 6.90,
    "StylePlus": "103",
    "RatingScore": 4.07,
    "AdjustedRating": "2.3922924850746060073939876977"
  },
  {
    "BID": 4012526,
    "BeerName": "Splitsville",
    "BeerStyle": "IPA - Milkshake",
    "BreweryName": "18th Street Brewery",
    "Origin": "Hammond, IN United States",
    "BeerAbv": 7.20,
    "BeerIbu": 0.00,
    "BeerLabel": "https://assets.untappd.com/site/beer_logos/beer-4012526_e6400_sm.jpeg",
    "HallRating": 13.93,
    "BAR": 6.90,
    "StylePlus": "102",
    "RatingScore": 3.87,
    "AdjustedRating": "2.3919933315535467869204227184"
  },
  {
    "BID": 6012959,
    "BeerName": "Plenty",
    "BeerStyle": "IPA - Imperial / Double New England / Hazy",
    "BreweryName": "Stepping Stone Brewing Company",
    "Origin": "Denmark",
    "BeerAbv": 8.10,
    "BeerIbu": 40.00,
    "BeerLabel": "https://assets.untappd.com/site/beer_logos/beer-6012959_49d82_sm.jpeg",
    "HallRating": 13.93,
    "BAR": 6.90,
    "StylePlus": "100",
    "RatingScore": 3.82,
    "AdjustedRating": "2.3919323795268586329815775993"
  },
  {
    "BID": 3339109,
    "BeerName": "Embrace Joy, Dammit",
    "BeerStyle": "Sour - Fruited",
    "BreweryName": "Pretentious Beer Co",
    "Origin": "Knoxville, TN United States",
    "BeerAbv": 3.80,
    "BeerIbu": 9.00,
    "BeerLabel": "https://assets.untappd.com/site/brewery_logos/brewery-175002_6ce24.jpeg",
    "HallRating": 13.93,
    "BAR": 4.48,
    "StylePlus": "102",
    "RatingScore": 3.99,
    "AdjustedRating": "2.3901203733264605251782508961"
  },
  {
    "BID": 4980544,
    "BeerName": "Furore",
    "BeerStyle": "Pale Ale - Belgian",
    "BreweryName": "Poggio Rosso",
    "Origin": "Italy",
    "BeerAbv": 6.80,
    "BeerIbu": 21.00,
    "BeerLabel": "https://assets.untappd.com/site/assets/images/temp/badge-beer-default.png",
    "HallRating": 13.93,
    "BAR": 4.48,
    "StylePlus": "115",
    "RatingScore": 3.71,
    "AdjustedRating": "2.3900769800524180017693792712"
  },
  {
    "BID": 4962130,
    "BeerName": "3 Fonteinen Cassis (season 21|22) Blend No. 26",
    "BeerStyle": "Lambic - Fruit",
    "BreweryName": "Brouwerij 3 Fonteinen",
    "Origin": "Beersel, Vlaams Gewest Belgium",
    "BeerAbv": 6.70,
    "BeerIbu": 0.00,
    "BeerLabel": "https://assets.untappd.com/site/beer_logos/beer-4962130_d7ab2_sm.jpeg",
    "HallRating": 13.93,
    "BAR": 6.91,
    "StylePlus": "103",
    "RatingScore": 4.16,
    "AdjustedRating": "2.3924353607112947491733521644"
  },
  {
    "BID": 3336914,
    "BeerName": "Golden Raspberry Sour",
    "BeerStyle": "Sour - Fruited",
    "BreweryName": "Emmett’s Brewing Co.",
    "Origin": "Palatine, IL United States",
    "BeerAbv": 0.00,
    "BeerIbu": 0.00,
    "BeerLabel": "https://assets.untappd.com/site/brewery_logos/brewery-EmmettsBrewingCo_500.jpeg",
    "HallRating": 13.93,
    "BAR": 4.48,
    "StylePlus": "102",
    "RatingScore": 3.81,
    "AdjustedRating": "2.3900924776502903315582619944"
  },
  {
    "BID": 6012254,
    "BeerName": "SEIDR",
    "BeerStyle": "Mead - Braggot",
    "BreweryName": "Vikingr Mead AS",
    "Origin": "Tveit, Agder Norway",
    "BeerAbv": 12.50,
    "BeerIbu": 0.00,
    "BeerLabel": "https://assets.untappd.com/site/beer_logos/beer-6012254_2acf3_sm.jpeg",
    "HallRating": 13.93,
    "BAR": 4.48,
    "StylePlus": "104",
    "RatingScore": 3.95,
    "AdjustedRating": "2.3901141742873115932626978068"
  },
  {
    "BID": 4447164,
    "BeerName": "BATCH 4000",
    "BeerStyle": "IPA - Imperial / Double",
    "BreweryName": "Phantom Canyon Brewing Company",
    "Origin": "Colorado Springs, CO United States",
    "BeerAbv": 10.00,
    "BeerIbu": 69.00,
    "BeerLabel": "https://assets.untappd.com/site/brewery_logos/brewery-4269_01856.jpeg",
    "HallRating": 13.93,
    "BAR": 4.48,
    "StylePlus": "101",
    "RatingScore": 3.71,
    "AdjustedRating": "2.3900769800524180017693792712"
  },
  {
    "BID": 3347814,
    "BeerName": "Lip Ripper Series - Calypso",
    "BeerStyle": "IPA - American",
    "BreweryName": "Grove Roots Brewing Company",
    "Origin": "Winter Haven, FL United States",
    "BeerAbv": 6.60,
    "BeerIbu": 0.00,
    "BeerLabel": "https://assets.untappd.com/site/brewery_logos/brewery-297078_655fd.jpeg",
    "HallRating": 13.93,
    "BAR": 4.48,
    "StylePlus": "104",
    "RatingScore": 3.57,
    "AdjustedRating": "2.3900552834153967400649434588"
  }
]
