[
  {
    "BID": 4001624,
    "BeerName": "Ambrogio15",
    "BeerStyle": "Lager - Euro Pale",
    "BreweryName": "Eppig Brewing",
    "Origin": "Vista, CA United States",
    "BeerAbv": 0.00,
    "BeerIbu": 0.00,
    "BeerLabel": "https://assets.untappd.com/site/brewery_logos/brewery-304405_69948.jpeg",
    "HallRating": 0.00,
    "BAR": 0.00,
    "StylePlus": null,
    "RatingScore": 0.00,
    "AdjustedRating": "2.3490465966145149722415184692"
  },
  {
    "BID": 2010521,
    "BeerName": "Erik's Bad Hombre",
    "BeerStyle": "Pale Ale - Other",
    "BreweryName": "Crazy Mountain Brewing Company",
    "Origin": "Edwards, CO United States",
    "BeerAbv": 6.00,
    "BeerIbu": 0.00,
    "BeerLabel": "https://assets.untappd.com/site/brewery_logos/brewery-4948_1201c.jpeg",
    "HallRating": 0.00,
    "BAR": 0.00,
    "StylePlus": null,
    "RatingScore": 0.00,
    "AdjustedRating": "2.3490231064421759813291824582"
  },
  {
    "BID": 1002394,
    "BeerName": "Sidamo",
    "BeerStyle": "Stout - Other",
    "BreweryName": "North Coast Brewing Company",
    "Origin": "Fort Bragg, CA United States",
    "BeerAbv": 5.00,
    "BeerIbu": 20.00,
    "BeerLabel": "https://assets.untappd.com/site/brewery_logos/brewery-NorthCoastBrewingCompany_919_d2110.jpeg",
    "HallRating": 0.00,
    "BAR": 0.00,
    "StylePlus": null,
    "RatingScore": 0.00,
    "AdjustedRating": "2.3490465966145149722415184692"
  },
  {
    "BID": 415,
    "BeerName": "Wee Heavy Winter Ale (Barrel Aged)",
    "BeerStyle": "Scotch Ale / Wee Heavy",
    "BreweryName": "Hale's Ales Brewery and Taproom",
    "Origin": "Seattle, WA United States",
    "BeerAbv": 7.40,
    "BeerIbu": 0.00,
    "BeerLabel": "https://assets.untappd.com/site/beer_logos/beer-105053_fa759_sm.jpeg",
    "HallRating": 0.00,
    "BAR": 0.00,
    "StylePlus": "103",
    "RatingScore": 3.65,
    "AdjustedRating": "2.3511339021528066358949274518"
  },
  {
    "BID": 22253,
    "BeerName": "Barrel Aged Oatmeal Porter",
    "BeerStyle": "Porter - American",
    "BreweryName": "Highland Brewing Company",
    "Origin": "Asheville, NC United States",
    "BeerAbv": 0.00,
    "BeerIbu": 0.00,
    "BeerLabel": "https://assets.untappd.com/site/brewery_logos/brewery-658_49b72.jpeg",
    "HallRating": 0.00,
    "BAR": 0.00,
    "StylePlus": "103",
    "RatingScore": 3.96,
    "AdjustedRating": "2.3495517082014640546720007528"
  },
  {
    "BID": 15084,
    "BeerName": "Worthington's White Shield",
    "BeerStyle": "IPA - English",
    "BreweryName": "Molson Coors (UK)",
    "Origin": "Burton-on-Trent, Staffordshire England",
    "BeerAbv": 5.60,
    "BeerIbu": 0.00,
    "BeerLabel": "https://assets.untappd.com/site/beer_logos/beer-15084_cda04_sm.jpeg",
    "HallRating": 0.00,
    "BAR": 0.00,
    "StylePlus": "86",
    "RatingScore": 3.36,
    "AdjustedRating": "2.3757310783522682768840080352"
  },
  {
    "BID": 6009622,
    "BeerName": "L'aumaloise",
    "BeerStyle": "Blonde / Golden Ale - Other",
    "BreweryName": "Les Deux Amants",
    "Origin": "Val-de-Reuil, Normandie France",
    "BeerAbv": 7.50,
    "BeerIbu": 0.00,
    "BeerLabel": "https://assets.untappd.com/site/brewery_logos/brewery-370238_f1310.jpeg",
    "HallRating": 0.00,
    "BAR": 0.00,
    "StylePlus": null,
    "RatingScore": 0.00,
    "AdjustedRating": "2.3490465966145149722415184692"
  },
  {
    "BID": 5000568,
    "BeerName": "60th Anniversary Lager",
    "BeerStyle": "Lager - Pale",
    "BreweryName": "Wenty Leagues",
    "Origin": "Wentworthville, New South Wales Australia",
    "BeerAbv": 0.00,
    "BeerIbu": 0.00,
    "BeerLabel": "https://assets.untappd.com/site/brewery_logos/brewery-528506_a2ba5.jpeg",
    "HallRating": 0.00,
    "BAR": 0.00,
    "StylePlus": null,
    "RatingScore": 0.00,
    "AdjustedRating": "2.3490348514696204863753012582"
  },
  {
    "BID": 4001625,
    "BeerName": "Semiprecious Fresh Hop IPA",
    "BeerStyle": "IPA - American",
    "BreweryName": "Elysian Brewing Company",
    "Origin": "Seattle, WA United States",
    "BeerAbv": 6.80,
    "BeerIbu": 0.00,
    "BeerLabel": "https://assets.untappd.com/site/beer_logos/beer-3978543_2a487_sm.jpeg",
    "HallRating": 0.00,
    "BAR": 0.00,
    "StylePlus": "104",
    "RatingScore": 3.62,
    "AdjustedRating": "2.3496939737742505120203787817"
  },
  {
    "BID": 2010522,
    "BeerName": "Lager Série #Black Lager",
    "BeerStyle": "Lager - Dark",
    "BreweryName": "La Brasserie du Mont Salève",
    "Origin": "Neydens, Auvergne-Rhône-Alpes France",
    "BeerAbv": 5.00,
    "BeerIbu": 0.00,
    "BeerLabel": "https://assets.untappd.com/site/beer_logos/beer-2010522_3f446_sm.jpeg",
    "HallRating": 0.00,
    "BAR": 0.00,
    "StylePlus": "111",
    "RatingScore": 3.72,
    "AdjustedRating": "2.3497033601349424108837792778"
  },
  {
    "BID": 1002395,
    "BeerName": "Mosaic #1",
    "BeerStyle": "IPA - Imperial / Double",
    "BreweryName": "Brygghus 9",
    "Origin": "Trondheim, Trøndelag Norway",
    "BeerAbv": 8.00,
    "BeerIbu": 0.00,
    "BeerLabel": "https://assets.untappd.com/site/brewery_logos/brewery-156844_8416e.jpeg",
    "HallRating": 0.00,
    "BAR": 0.00,
    "StylePlus": "101",
    "RatingScore": 3.96,
    "AdjustedRating": "2.3492336804419567883902551693"
  },
  {
    "BID": 4150,
    "BeerName": "Capitol Kölsch",
    "BeerStyle": "Kölsch",
    "BreweryName": "Capitol City Brewing Company",
    "Origin": "Washington, DC United States",
    "BeerAbv": 5.20,
    "BeerIbu": 19.00,
    "BeerLabel": "https://assets.untappd.com/site/beer_logos/beer-4150_556f5_sm.jpeg",
    "HallRating": 0.00,
    "BAR": 0.00,
    "StylePlus": "82",
    "RatingScore": 3.38,
    "AdjustedRating": "2.3716126159799940907340025998"
  },
  {
    "BID": 22254,
    "BeerName": "Coconut Joe",
    "BeerStyle": "Scottish Ale",
    "BreweryName": "Sun King Brewery",
    "Origin": "Indianapolis, IN United States",
    "BeerAbv": 5.30,
    "BeerIbu": 23.00,
    "BeerLabel": "https://assets.untappd.com/site/beer_logos/beer-22254_98c82_sm.jpeg",
    "HallRating": 0.00,
    "BAR": 0.00,
    "StylePlus": "109",
    "RatingScore": 3.88,
    "AdjustedRating": "2.3491175317359077324503199344"
  },
  {
    "BID": 15085,
    "BeerName": "Stand Blonde Ale",
    "BeerStyle": "Blonde / Golden Ale - Other",
    "BreweryName": "Golden Road Brewing",
    "Origin": "Los Angeles, CA United States",
    "BeerAbv": 5.30,
    "BeerIbu": 0.00,
    "BeerLabel": "https://assets.untappd.com/site/brewery_logos/brewery-16302_91b59.jpeg",
    "HallRating": 0.00,
    "BAR": 0.00,
    "StylePlus": "86",
    "RatingScore": 3.48,
    "AdjustedRating": "2.3491994732994775764440113515"
  },
  {
    "BID": 6009624,
    "BeerName": "Anniversary IPA (2024)",
    "BeerStyle": "IPA - New England / Hazy",
    "BreweryName": "Double Nickel Brewing Company",
    "Origin": "Pennsauken, NJ United States",
    "BeerAbv": 7.70,
    "BeerIbu": 22.00,
    "BeerLabel": "https://assets.untappd.com/site/brewery_logos/brewery-232550_420fc.jpeg",
    "HallRating": 0.00,
    "BAR": 0.00,
    "StylePlus": "101",
    "RatingScore": 3.92,
    "AdjustedRating": "2.3498807071579806737235598952"
  },
  {
    "BID": 5000569,
    "BeerName": "Escape - Pina Coloda Sour",
    "BeerStyle": "Sour - Other",
    "BreweryName": "North Basin Brewing Co",
    "Origin": "Osoyoos, BC Canada",
    "BeerAbv": 4.50,
    "BeerIbu": 0.00,
    "BeerLabel": "https://assets.untappd.com/site/brewery_logos/brewery-482257_b3b0a.jpeg",
    "HallRating": 0.00,
    "BAR": 0.00,
    "StylePlus": null,
    "RatingScore": 0.00,
    "AdjustedRating": "2.3490407240273863715970910875"
  },
  {
    "BID": 4001717,
    "BeerName": "BubbleFest Tonka Bean Red IPA",
    "BeerStyle": "IPA - Red",
    "BreweryName": "Bassline Brewing",
    "Origin": "Karori, Wellington New Zealand",
    "BeerAbv": 6.50,
    "BeerIbu": 40.00,
    "BeerLabel": "https://assets.untappd.com/site/beer_logos/beer-4001717_92d27_sm.jpeg",
    "HallRating": 0.00,
    "BAR": 0.00,
    "StylePlus": "106",
    "RatingScore": 3.79,
    "AdjustedRating": "2.349653813763760138671053908"
  },
  {
    "BID": 2010523,
    "BeerName": "Cosmic Haze",
    "BeerStyle": "IPA - American",
    "BreweryName": "Kindred Spirit Brewing",
    "Origin": "Goochland, VA United States",
    "BeerAbv": 6.50,
    "BeerIbu": 0.00,
    "BeerLabel": "https://assets.untappd.com/site/brewery_logos/brewery-273907_025b0.jpeg",
    "HallRating": 0.00,
    "BAR": 0.00,
    "StylePlus": "104",
    "RatingScore": 3.68,
    "AdjustedRating": "2.3497641454132104409430445442"
  },
  {
    "BID": 1002396,
    "BeerName": "Hope St Hops",
    "BeerStyle": "Pale Ale - English",
    "BreweryName": "Mad Hatter Brewing Company",
    "Origin": "Liverpool, Merseyside England",
    "BeerAbv": 4.50,
    "BeerIbu": 0.00,
    "BeerLabel": "https://assets.untappd.com/site/brewery_logos/brewery-MadHatterBrewingCompany_60772.jpeg",
    "HallRating": 0.00,
    "BAR": 0.00,
    "StylePlus": "117",
    "RatingScore": 3.64,
    "AdjustedRating": "2.3493525447643487974335457736"
  },
  {
    "BID": 4152,
    "BeerName": "Irish Red Ale",
    "BeerStyle": "Red Ale - Irish",
    "BreweryName": "Capitol City Brewing Company",
    "Origin": "Washington, DC United States",
    "BeerAbv": 5.50,
    "BeerIbu": 0.00,
    "BeerLabel": "https://assets.untappd.com/site/brewery_logos/brewery-3652_30421.jpeg",
    "HallRating": 0.00,
    "BAR": 0.00,
    "StylePlus": "82",
    "RatingScore": 3.47,
    "AdjustedRating": "2.35037921985547776737461016"
  },
  {
    "BID": 22255,
    "BeerName": "Old Richland (Provisions Series)",
    "BeerStyle": "Barleywine - American",
    "BreweryName": "The Bruery",
    "Origin": "Placentia, CA United States",
    "BeerAbv": 9.00,
    "BeerIbu": 0.00,
    "BeerLabel": "https://assets.untappd.com/site/beer_logos/beer-brueryOldRichland.jpg",
    "HallRating": 0.00,
    "BAR": 0.00,
    "StylePlus": "102",
    "RatingScore": 3.81,
    "AdjustedRating": "2.3538758803772568452291275879"
  },
  {
    "BID": 15086,
    "BeerName": "CCBR Lager",
    "BeerStyle": "Lager - American",
    "BreweryName": "Central Coast Brewing",
    "Origin": "San Luis Obispo, CA United States",
    "BeerAbv": 0.00,
    "BeerIbu": 0.00,
    "BeerLabel": "https://assets.untappd.com/site/brewery_logos/brewery-centralcoastbrewing_3886.jpeg",
    "HallRating": 0.00,
    "BAR": 0.00,
    "StylePlus": null,
    "RatingScore": 0.00,
    "AdjustedRating": "2.3490407240273863715970910875"
  },
  {
    "BID": 6009625,
    "BeerName": "Apa Lederhosen",
    "BeerStyle": "IPA - American",
    "BreweryName": "Kullens Bryggeri",
    "Origin": "Höganäs, Skåne län Sweden",
    "BeerAbv": 5.20,
    "BeerIbu": 0.00,
    "BeerLabel": "https://assets.untappd.com/site/brewery_logos/brewery-297086_8c916.jpeg",
    "HallRating": 0.00,
    "BAR": 0.00,
    "StylePlus": null,
    "RatingScore": 0.00,
    "AdjustedRating": "2.3490465966145149722415184692"
  },
  {
    "BID": 5000570,
    "BeerName": "Stone Mo's IPA",
    "BeerStyle": "IPA - American",
    "BreweryName": "Stone Brewing",
    "Origin": "Escondido, CA United States",
    "BeerAbv": 6.20,
    "BeerIbu": 0.00,
    "BeerLabel": "https://assets.untappd.com/site/brewery_logos/brewery-1204_a1e0b.jpeg",
    "HallRating": 0.00,
    "BAR": 0.00,
    "StylePlus": "104",
    "RatingScore": 3.66,
    "AdjustedRating": "2.3491049050348051163242961012"
  },
  {
    "BID": 4001718,
    "BeerName": "Night Shift Dark Ale",
    "BeerStyle": "Dark Ale",
    "BreweryName": "Black Horse Brewery",
    "Origin": "Magaliesburg, Gauteng South Africa",
    "BeerAbv": 4.20,
    "BeerIbu": 0.00,
    "BeerLabel": "https://assets.untappd.com/site/brewery_logos/brewery-136757_a9eef.jpeg",
    "HallRating": 0.00,
    "BAR": 0.00,
    "StylePlus": "83",
    "RatingScore": 2.96,
    "AdjustedRating": "2.3491227201181929163435695625"
  }
]
