[
  {
    "BID": 2004702,
    "BeerName": "One Off Wednesday: St. Patrick's Day Stout Variety",
    "BeerStyle": "Stout - Other",
    "BreweryName": "Cape May Brewing Co.",
    "Origin": "Cape May, NJ United States",
    "BeerAbv": 4.70,
    "BeerIbu": 0.00,
    "BeerLabel": "https://assets.untappd.com/site/brewery_logos/brewery-13805_c569e.jpeg",
    "HallRating": 0.00,
    "BAR": 0.00,
    "StylePlus": "106",
    "RatingScore": 3.86,
    "AdjustedRating": "2.3901369673302066893555695225"
  },
  {
    "BID": 2004087,
    "BeerName": "Bourbon Barrel Aged Dunkel",
    "BeerStyle": "Lager - Munich Dunkel",
    "BreweryName": "Schulz Bräu Brewing Company",
    "Origin": "Knoxville, TN United States",
    "BeerAbv": 8.20,
    "BeerIbu": 26.00,
    "BeerLabel": "https://assets.untappd.com/site/beer_logos/beer-1998019_02105_sm.jpeg",
    "HallRating": 0.00,
    "BAR": 0.00,
    "StylePlus": "113",
    "RatingScore": 3.98,
    "AdjustedRating": "2.3905955709995213443479751963"
  },
  {
    "BID": 3346651,
    "BeerName": "Anotha One",
    "BeerStyle": "Pale Ale - American",
    "BreweryName": "Millennial Brewing Company",
    "Origin": "Fort Myers, FL United States",
    "BeerAbv": 4.75,
    "BeerIbu": 0.00,
    "BeerLabel": "https://assets.untappd.com/site/brewery_logos/brewery-291736_367fd.jpeg",
    "HallRating": 0.00,
    "BAR": 0.00,
    "StylePlus": "82",
    "RatingScore": 3.31,
    "AdjustedRating": "2.3899091956165014665009934853"
  },
  {
    "BID": 2002593,
    "BeerName": "Hemisphere Grisette",
    "BeerStyle": "Farmhouse Ale - Grisette",
    "BreweryName": "Hemisphere Brewing",
    "Origin": "Rockwall, TX United States",
    "BeerAbv": 5.56,
    "BeerIbu": 15.00,
    "BeerLabel": "https://assets.untappd.com/site/brewery_logos/brewery-330978_2ab59.jpeg",
    "HallRating": 0.00,
    "BAR": 0.00,
    "StylePlus": "106",
    "RatingScore": 3.58,
    "AdjustedRating": "2.3903036569086967239972045384"
  },
  {
    "BID": 4002024,
    "BeerName": "Gammel Traver - En Meny Vollebekk Juleøl",
    "BeerStyle": "Brown Ale - Other",
    "BreweryName": "St. Hallvards Bryggeri AS",
    "Origin": "Kalbakken, Oslo Norway",
    "BeerAbv": 4.70,
    "BeerIbu": 0.00,
    "BeerLabel": "https://assets.untappd.com/site/beer_logos/beer-4002024_71789_sm.jpeg",
    "HallRating": 0.00,
    "BAR": 0.00,
    "StylePlus": "82",
    "RatingScore": 3.16,
    "AdjustedRating": "2.3899763451777271333966449779"
  },
  {
    "BID": 5004141,
    "BeerName": "Die Helle Seite",
    "BeerStyle": "Pilsner - German",
    "BreweryName": "Wagerswiler Bräu",
    "Origin": "Wagerswil, Thurgau Switzerland",
    "BeerAbv": 5.30,
    "BeerIbu": 35.00,
    "BeerLabel": "https://assets.untappd.com/site/beer_logos/beer-5004141_d308f_sm.jpeg",
    "HallRating": 0.00,
    "BAR": 0.00,
    "StylePlus": null,
    "RatingScore": 0.00,
    "AdjustedRating": "2.3898544680758155579429689527"
  },
  {
    "BID": 2016346,
    "BeerName": "Vedett Extra IPA",
    "BeerStyle": "IPA - Belgian",
    "BreweryName": "Duvel Moortgat",
    "Origin": "Puurs-Sint-Amands, Vlaams Gewest Belgium",
    "BeerAbv": 5.50,
    "BeerIbu": 40.00,
    "BeerLabel": "https://assets.untappd.com/site/beer_logos/beer-603235_db51d_sm.jpeg",
    "HallRating": 0.00,
    "BAR": 0.00,
    "StylePlus": null,
    "RatingScore": 3.48,
    "AdjustedRating": null
  },
  {
    "BID": 1667436,
    "BeerName": "Four Year Storm",
    "BeerStyle": "Stout - Imperial / Double",
    "BreweryName": "Big Storm Brewing Co.",
    "Origin": "Clearwater, FL United States",
    "BeerAbv": 9.10,
    "BeerIbu": 60.00,
    "BeerLabel": "https://assets.untappd.com/site/beer_logos/beer-1667436_ef291_sm.jpeg",
    "HallRating": 0.00,
    "BAR": 0.00,
    "StylePlus": "100",
    "RatingScore": 3.86,
    "AdjustedRating": "2.5597797966786550218389217402"
  },
  {
    "BID": 2004703,
    "BeerName": "Dowd's Irish Red",
    "BeerStyle": "Red Ale - Irish",
    "BreweryName": "Tampa Bay Brewing Company",
    "Origin": "Tampa, FL United States",
    "BeerAbv": 5.00,
    "BeerIbu": 30.00,
    "BeerLabel": "https://assets.untappd.com/site/brewery_logos/brewery-4530_a77e4.jpeg",
    "HallRating": 0.00,
    "BAR": 0.00,
    "StylePlus": null,
    "RatingScore": 0.00,
    "AdjustedRating": "2.3898186210653521561361404618"
  },
  {
    "BID": 2004088,
    "BeerName": "Blueberry Uncommon Stout",
    "BeerStyle": "Stout - Coffee",
    "BreweryName": "Bent River Brewing Company",
    "Origin": "Moline, IL United States",
    "BeerAbv": 5.50,
    "BeerIbu": 31.00,
    "BeerLabel": "https://assets.untappd.com/site/brewery_logos/brewery-102_59957.jpeg",
    "HallRating": 0.00,
    "BAR": 0.00,
    "StylePlus": "103",
    "RatingScore": 3.57,
    "AdjustedRating": "2.3968642808703389066758653674"
  },
  {
    "BID": 3346654,
    "BeerName": "Roxane",
    "BeerStyle": "Cream Ale",
    "BreweryName": "Kawâ Bieres & Cie",
    "Origin": "Terrebonne, QC Canada",
    "BeerAbv": 5.50,
    "BeerIbu": 0.00,
    "BeerLabel": "https://assets.untappd.com/site/assets/images/temp/badge-beer-default.png",
    "HallRating": 0.00,
    "BAR": 0.00,
    "StylePlus": "82",
    "RatingScore": 3.38,
    "AdjustedRating": "2.389911995504505946321800653"
  },
  {
    "BID": 2002594,
    "BeerName": "Piraat (2017)",
    "BeerStyle": "Belgian Strong Golden Ale",
    "BreweryName": "Brouwerij Van Steenberge",
    "Origin": "Evergem, Vlaams Gewest Belgium",
    "BeerAbv": 10.50,
    "BeerIbu": 23.00,
    "BeerLabel": "https://assets.untappd.com/site/beer_logos/beer-11561_1b366_sm.jpeg",
    "HallRating": 0.00,
    "BAR": 0.00,
    "StylePlus": "106",
    "RatingScore": 3.72,
    "AdjustedRating": "2.3925770163135871926546197373"
  },
  {
    "BID": 4002025,
    "BeerName": "Dikke Jan Bruin Oak Aged",
    "BeerStyle": "Brown Ale - Belgian",
    "BreweryName": "Brouwerij Dikke Jan",
    "Origin": "Waregem, Vlaams Gewest Belgium",
    "BeerAbv": 8.50,
    "BeerIbu": 0.00,
    "BeerLabel": "https://assets.untappd.com/site/brewery_logos/brewery-154772_369e6.jpeg",
    "HallRating": 0.00,
    "BAR": 0.00,
    "StylePlus": "87",
    "RatingScore": 3.14,
    "AdjustedRating": "2.389902395888490586936176078"
  },
  {
    "BID": 5004142,
    "BeerName": "Skull Session",
    "BeerStyle": "Porter - Coffee",
    "BreweryName": "Somewhere In Particular Brewing",
    "Origin": "Columbus, OH United States",
    "BeerAbv": 7.10,
    "BeerIbu": 0.00,
    "BeerLabel": "https://assets.untappd.com/site/brewery_logos/brewery-409176_676cb.jpeg",
    "HallRating": 0.00,
    "BAR": 0.00,
    "StylePlus": "102",
    "RatingScore": 3.86,
    "AdjustedRating": "2.3908457067036349683930931008"
  },
  {
    "BID": 2016353,
    "BeerName": "Haystack",
    "BeerStyle": "Wheat Beer - Hefeweizen",
    "BreweryName": "Snoqualmie Falls Brewing Company",
    "Origin": "Snoqualmie, WA United States",
    "BeerAbv": 5.30,
    "BeerIbu": 18.00,
    "BeerLabel": "https://assets.untappd.com/site/beer_logos/beer-21098_88b26_sm.jpeg",
    "HallRating": 0.00,
    "BAR": 0.00,
    "StylePlus": null,
    "RatingScore": 3.57,
    "AdjustedRating": null
  },
  {
    "BID": 1667439,
    "BeerName": "Drinkin Buddy Amber Ale",
    "BeerStyle": "Red Ale - Other",
    "BreweryName": "Newaygo Brewing Co.",
    "Origin": "Newaygo, MI United States",
    "BeerAbv": 5.00,
    "BeerIbu": 42.00,
    "BeerLabel": "https://assets.untappd.com/site/brewery_logos/brewery-197624_b9817.jpeg",
    "HallRating": 0.00,
    "BAR": 0.00,
    "StylePlus": "85",
    "RatingScore": 3.43,
    "AdjustedRating": "2.3901427548680604308476331404"
  },
  {
    "BID": 2004704,
    "BeerName": "Sweet Bean",
    "BeerStyle": "Brown Ale - Other",
    "BreweryName": "BriarScratch Brewing",
    "Origin": "Gallatin, TN United States",
    "BeerAbv": 4.10,
    "BeerIbu": 16.00,
    "BeerLabel": "https://assets.untappd.com/site/brewery_logos/brewery-BriarScratchBrewing_30919_659b5.jpeg",
    "HallRating": 0.00,
    "BAR": 0.00,
    "StylePlus": null,
    "RatingScore": 0.00,
    "AdjustedRating": "2.3898664173182828308525763936"
  },
  {
    "BID": 2004090,
    "BeerName": "Kûarasy",
    "BeerStyle": "Lager - Vienna",
    "BreweryName": "Cervejaria Xamã",
    "Origin": "Curitiba, Paraná Brazil",
    "BeerAbv": 5.50,
    "BeerIbu": 25.00,
    "BeerLabel": "https://assets.untappd.com/site/beer_logos/beer-1961260_2a276_sm.jpeg",
    "HallRating": 0.00,
    "BAR": 0.00,
    "StylePlus": "113",
    "RatingScore": 3.92,
    "AdjustedRating": "2.3901401174637699668154608194"
  },
  {
    "BID": 3346498,
    "BeerName": "*Cask* Sweet Cherry Ale",
    "BeerStyle": "Mild - Other",
    "BreweryName": "Willimantic Brewing Company",
    "Origin": "Willimantic, CT United States",
    "BeerAbv": 5.20,
    "BeerIbu": 0.00,
    "BeerLabel": "https://assets.untappd.com/site/brewery_logos/brewery-3713_8ed50.jpeg",
    "HallRating": 0.00,
    "BAR": 0.00,
    "StylePlus": null,
    "RatingScore": 0.00,
    "AdjustedRating": null
  },
  {
    "BID": 2002597,
    "BeerName": "Bobcat 2.0",
    "BeerStyle": "Farmhouse Ale - Saison",
    "BreweryName": "Ramses Bier",
    "Origin": "Hooge Zwaluwe, Noord-Brabant Netherlands",
    "BeerAbv": 7.70,
    "BeerIbu": 0.00,
    "BeerLabel": "https://assets.untappd.com/site/beer_logos/beer-2002597_da2d4_sm.jpeg",
    "HallRating": 0.00,
    "BAR": 0.00,
    "StylePlus": "79",
    "RatingScore": 3.33,
    "AdjustedRating": "2.3917067552777581094556676947"
  },
  {
    "BID": 4002026,
    "BeerName": "Rastaværing - En Meny Rasta Juleøl",
    "BeerStyle": "Brown Ale - Other",
    "BreweryName": "St. Hallvards Bryggeri AS",
    "Origin": "Kalbakken, Oslo Norway",
    "BeerAbv": 4.70,
    "BeerIbu": 0.00,
    "BeerLabel": "https://assets.untappd.com/site/beer_logos/beer-4002026_4e3a6_sm.jpeg",
    "HallRating": 0.00,
    "BAR": 0.00,
    "StylePlus": "82",
    "RatingScore": 2.90,
    "AdjustedRating": "2.3899335999523318467380449596"
  },
  {
    "BID": 5004143,
    "BeerName": "Kaijuice",
    "BeerStyle": "IPA - New England / Hazy",
    "BreweryName": "Roughtail Brewing Company",
    "Origin": "Oklahoma City, OK United States",
    "BeerAbv": 8.25,
    "BeerIbu": 0.00,
    "BeerLabel": "https://assets.untappd.com/site/brewery_logos/brewery-58550_9ab24.jpeg",
    "HallRating": 0.00,
    "BAR": 0.00,
    "StylePlus": "101",
    "RatingScore": 4.17,
    "AdjustedRating": "2.3901794110359224299404887907"
  },
  {
    "BID": 2016326,
    "BeerName": "MiniMilk",
    "BeerStyle": "Stout - Milk / Sweet",
    "BreweryName": "SingleSpeed Brewing Company",
    "Origin": "Waterloo, IA United States",
    "BeerAbv": 4.60,
    "BeerIbu": 30.00,
    "BeerLabel": "https://assets.untappd.com/site/beer_logos/beer-2016326_1e592_sm.jpeg",
    "HallRating": 0.00,
    "BAR": 0.00,
    "StylePlus": null,
    "RatingScore": 3.91,
    "AdjustedRating": null
  },
  {
    "BID": 1667431,
    "BeerName": "Tamarindo Red Coffee Saison",
    "BeerStyle": "Farmhouse Ale - Saison",
    "BreweryName": "O'Connor Brewing Co.",
    "Origin": "Norfolk, VA United States",
    "BeerAbv": 7.00,
    "BeerIbu": 20.00,
    "BeerLabel": "https://assets.untappd.com/site/beer_logos/beer-1666368_9a82b_sm.jpeg",
    "HallRating": 0.00,
    "BAR": 0.00,
    "StylePlus": "105",
    "RatingScore": 3.69,
    "AdjustedRating": "2.560997863418980558456525071"
  },
  {
    "BID": 2004706,
    "BeerName": "American Barleywine",
    "BeerStyle": "Barleywine - American",
    "BreweryName": "Brasseria Della Fonte",
    "Origin": "Pienza, Toscana Italy",
    "BeerAbv": 11.00,
    "BeerIbu": 100.00,
    "BeerLabel": "https://assets.untappd.com/site/beer_logos/beer-2004706_3c399_sm.jpeg",
    "HallRating": 0.00,
    "BAR": 0.00,
    "StylePlus": "102",
    "RatingScore": 3.95,
    "AdjustedRating": "2.3902857162695147051627853869"
  }
]
