[
  {
    "BID": 5203495,
    "BeerName": "Que Nice",
    "BeerStyle": "Lager - Mexican",
    "BreweryName": "Project Halo Brewing",
    "Origin": "Fulshear, TX United States",
    "BeerAbv": 5.50,
    "BeerIbu": 0.00,
    "BeerLabel": "https://assets.untappd.com/site/beer_logos/beer-5203495_1c070_sm.jpeg",
    "HallRating": 13.82,
    "BAR": 4.72,
    "StylePlus": "103",
    "RatingScore": 3.75,
    "AdjustedRating": "2.1196458431751887761605890866"
  },
  {
    "BID": 5601021,
    "BeerName": "Clouds Over Clermont",
    "BeerStyle": "IPA - New England / Hazy",
    "BreweryName": "Lasting Joy Brewery",
    "Origin": "Tivoli, NY United States",
    "BeerAbv": 6.50,
    "BeerIbu": 0.00,
    "BeerLabel": "https://assets.untappd.com/site/beer_logos/beer-5462175_3ef94_sm.jpeg",
    "HallRating": 13.82,
    "BAR": 6.57,
    "StylePlus": "98",
    "RatingScore": 3.79,
    "AdjustedRating": "2.1211010329051205721934749166"
  },
  {
    "BID": 5304072,
    "BeerName": "Lightbringer",
    "BeerStyle": "IPA - Belgian",
    "BreweryName": "Vega Bryggeri",
    "Origin": "Gothenburg, Västra Götalands län Sweden",
    "BeerAbv": 9.20,
    "BeerIbu": 0.00,
    "BeerLabel": "https://assets.untappd.com/site/brewery_logos/brewery-30350_98c89.jpeg",
    "HallRating": 13.82,
    "BAR": 6.55,
    "StylePlus": "102",
    "RatingScore": 3.67,
    "AdjustedRating": "2.1209430192599696315831535203"
  },
  {
    "BID": 4411054,
    "BeerName": "Morningcider Dry Cider",
    "BeerStyle": "Cider - Dry",
    "BreweryName": "Morningcider",
    "Origin": "Auckland, New Zealand",
    "BeerAbv": 4.90,
    "BeerIbu": 0.00,
    "BeerLabel": "https://assets.untappd.com/site/beer_logos/beer-3590645_fdb5c_sm.jpeg",
    "HallRating": 13.82,
    "BAR": 6.56,
    "StylePlus": "101",
    "RatingScore": 3.70,
    "AdjustedRating": "2.1209860171470384771951380928"
  },
  {
    "BID": 6303297,
    "BeerName": "Time To NZ",
    "BeerStyle": "Pilsner - New Zealand",
    "BreweryName": "Croma",
    "Origin": "São Paulo, Brazil",
    "BeerAbv": 5.50,
    "BeerIbu": 0.00,
    "BeerLabel": "https://assets.untappd.com/site/beer_logos/beer-6303297_d2e68_sm.jpeg",
    "HallRating": 13.82,
    "BAR": 4.73,
    "StylePlus": "105",
    "RatingScore": 3.92,
    "AdjustedRating": "2.1196830618029484250571138628"
  },
  {
    "BID": 6414039,
    "BeerName": "Mash My Brain",
    "BeerStyle": "IPA - Imperial / Double New England / Hazy",
    "BreweryName": "Tripping Animals Brewing Co.",
    "Origin": "Doral, FL United States",
    "BeerAbv": 8.10,
    "BeerIbu": 0.00,
    "BeerLabel": "https://assets.untappd.com/site/beer_logos/beer-6414039_252e2_sm.jpeg",
    "HallRating": 13.82,
    "BAR": 6.56,
    "StylePlus": "101",
    "RatingScore": 4.08,
    "AdjustedRating": "2.1213885420308675890315169072"
  },
  {
    "BID": 1906416,
    "BeerName": "Artaban",
    "BeerStyle": "Belgian Strong Dark Ale",
    "BreweryName": "Conclave Brewing",
    "Origin": "Flemington, NJ United States",
    "BeerAbv": 9.20,
    "BeerIbu": 0.00,
    "BeerLabel": "https://assets.untappd.com/site/beer_logos/beer-3595484_a835a_sm.jpeg",
    "HallRating": 13.82,
    "BAR": 6.54,
    "StylePlus": "105",
    "RatingScore": 3.97,
    "AdjustedRating": "2.1212408438287468189094759661"
  },
  {
    "BID": 4962101,
    "BeerName": "Sunrise",
    "BeerStyle": "IPA - New England / Hazy",
    "BreweryName": "Skudenes Bryggeri",
    "Origin": "Skudeneshavn, Rogaland Norway",
    "BeerAbv": 7.00,
    "BeerIbu": 25.00,
    "BeerLabel": "https://assets.untappd.com/site/beer_logos/beer-4808788_f696f_sm.jpeg",
    "HallRating": 13.82,
    "BAR": 6.56,
    "StylePlus": "94",
    "RatingScore": 3.64,
    "AdjustedRating": "2.1209308203116220178262378846"
  },
  {
    "BID": 5402181,
    "BeerName": "Ceriņu Vecis (Lilac Elder)",
    "BeerStyle": "Wild Ale - Other",
    "BreweryName": "Labietis. Pagan Brews",
    "Origin": "Latvia",
    "BeerAbv": 6.60,
    "BeerIbu": 0.00,
    "BeerLabel": "https://assets.untappd.com/site/beer_logos/beer-5402181_4c9cd_sm.jpeg",
    "HallRating": 13.82,
    "BAR": 6.55,
    "StylePlus": "98",
    "RatingScore": 3.87,
    "AdjustedRating": "2.1211464355730929160995467203"
  },
  {
    "BID": 5601720,
    "BeerName": "Гарбуз (2023)",
    "BeerStyle": "Pumpkin / Yam Beer",
    "BreweryName": "Pravda Brewery",
    "Origin": "L'viv, L'vivs'ka oblast Ukraine",
    "BeerAbv": 7.00,
    "BeerIbu": 14.00,
    "BeerLabel": "https://assets.untappd.com/site/beer_logos/beer-5591319_006a2_sm.jpeg",
    "HallRating": 13.82,
    "BAR": 4.72,
    "StylePlus": "104",
    "RatingScore": 3.85,
    "AdjustedRating": "2.1196650894702769716829510319"
  },
  {
    "BID": 5303991,
    "BeerName": "Binalong Pale",
    "BeerStyle": "Pale Ale - American",
    "BreweryName": "Manchild Brewing",
    "Origin": "St Helens, Tasmania Australia",
    "BeerAbv": 4.80,
    "BeerIbu": 0.00,
    "BeerLabel": "https://assets.untappd.com/site/beer_logos/beer-5548442_a20b6_sm.jpeg",
    "HallRating": 13.82,
    "BAR": 4.72,
    "StylePlus": "98",
    "RatingScore": 3.53,
    "AdjustedRating": "2.1196035013259947460113928069"
  },
  {
    "BID": 4409464,
    "BeerName": "Lawless Latte",
    "BeerStyle": "Stout - White / Golden",
    "BreweryName": "Lawless Brewing Co.",
    "Origin": "Los Angeles, CA United States",
    "BeerAbv": 6.50,
    "BeerIbu": 26.00,
    "BeerLabel": "https://assets.untappd.com/site/brewery_logos/brewery-447714_bf0f2.jpeg",
    "HallRating": 13.82,
    "BAR": 6.56,
    "StylePlus": "106",
    "RatingScore": 4.04,
    "AdjustedRating": "2.1213465860846111582838020079"
  },
  {
    "BID": 6106083,
    "BeerName": "Wally Double IPA",
    "BeerStyle": "IPA - New England / Hazy",
    "BreweryName": "Hooglander Bier",
    "Origin": "Aarle-Rixtel, Noord-Brabant Netherlands",
    "BeerAbv": 8.00,
    "BeerIbu": 0.00,
    "BeerLabel": "https://assets.untappd.com/site/brewery_logos/brewery-206413_f604f.jpeg",
    "HallRating": 13.82,
    "BAR": 4.72,
    "StylePlus": "101",
    "RatingScore": 3.89,
    "AdjustedRating": "2.1196727879883122498918958101"
  },
  {
    "BID": 3602085,
    "BeerName": "Dutchess of Oltorf",
    "BeerStyle": "Historical Beer - Roggenbier",
    "BreweryName": "Hopsquad Brewing",
    "Origin": "Austin, TX United States",
    "BeerAbv": 4.30,
    "BeerIbu": 0.00,
    "BeerLabel": "https://assets.untappd.com/site/beer_logos/beer-3602085_040a6_sm.jpeg",
    "HallRating": 13.82,
    "BAR": 6.54,
    "StylePlus": "98",
    "RatingScore": 3.54,
    "AdjustedRating": "2.1207973267601201759183642889"
  },
  {
    "BID": 1611053,
    "BeerName": "Kenmare Traditional Irish Stout",
    "BeerStyle": "Stout - Irish Dry",
    "BreweryName": "Little Island Brewing Company",
    "Origin": "Perth, Western Australia Australia",
    "BeerAbv": 4.50,
    "BeerIbu": 30.00,
    "BeerLabel": "https://assets.untappd.com/site/assets/images/temp/badge-beer-default.png",
    "HallRating": 13.82,
    "BAR": 6.57,
    "StylePlus": "102",
    "RatingScore": 3.72,
    "AdjustedRating": "2.1210309046637947181120059936"
  },
  {
    "BID": 4961814,
    "BeerName": "Into the 'Wood: Whiskey Barrel-Aged Strong Ale With Coffee (2022)",
    "BeerStyle": "Strong Ale - Other",
    "BreweryName": "Stomping Ground Brewing Co.",
    "Origin": "Collingwood, Victoria Australia",
    "BeerAbv": 10.00,
    "BeerIbu": 0.00,
    "BeerLabel": "https://assets.untappd.com/site/beer_logos/beer-4961814_08d39_sm.jpeg",
    "HallRating": 13.82,
    "BAR": 4.73,
    "StylePlus": "103",
    "RatingScore": 3.95,
    "AdjustedRating": "2.1196889106624208279385519824"
  },
  {
    "BID": 5027901,
    "BeerName": "Artist Juice",
    "BeerStyle": "Sour - Smoothie / Pastry",
    "BreweryName": "Mad Scientist",
    "Origin": "Hungary",
    "BeerAbv": 3.40,
    "BeerIbu": 0.00,
    "BeerLabel": "https://assets.untappd.com/site/beer_logos/beer-5027901_7781b_sm.jpeg",
    "HallRating": 13.82,
    "BAR": 6.54,
    "StylePlus": "96",
    "RatingScore": 3.88,
    "AdjustedRating": "2.1211436220692686532871142723"
  },
  {
    "BID": 5550778,
    "BeerName": "Re-Tired Amber Ale",
    "BeerStyle": "Red Ale - American Amber / Red",
    "BreweryName": "Crooked Stave Brewing Co.",
    "Origin": "Denver, CO United States",
    "BeerAbv": 6.00,
    "BeerIbu": 0.00,
    "BeerLabel": "https://assets.untappd.com/site/brewery_logos/brewery-10568_afc6c.jpeg",
    "HallRating": 13.82,
    "BAR": 6.57,
    "StylePlus": "104",
    "RatingScore": 3.67,
    "AdjustedRating": "2.1209739675943499890116476535"
  },
  {
    "BID": 4941652,
    "BeerName": "Adjective+Noun",
    "BeerStyle": "IPA - New England / Hazy",
    "BreweryName": "Hop Farm Brewing Company",
    "Origin": "Lawrenceville, PA United States",
    "BeerAbv": 7.90,
    "BeerIbu": 0.00,
    "BeerLabel": "https://assets.untappd.com/site/beer_logos/beer-4941652_67422_sm.jpeg",
    "HallRating": 13.82,
    "BAR": 6.55,
    "StylePlus": "102",
    "RatingScore": 3.94,
    "AdjustedRating": "2.1212280697372988659322656131"
  },
  {
    "BID": 4408849,
    "BeerName": "Repetitions On Citra",
    "BeerStyle": "IPA - Imperial / Double New England / Hazy",
    "BreweryName": "BKS Artisan Ales",
    "Origin": "Kansas City, MO United States",
    "BeerAbv": 8.50,
    "BeerIbu": 0.00,
    "BeerLabel": "https://assets.untappd.com/site/beer_logos/beer-4408849_2e858_sm.jpeg",
    "HallRating": 13.82,
    "BAR": 6.56,
    "StylePlus": "109",
    "RatingScore": 4.38,
    "AdjustedRating": "2.121708851433865856186363852"
  },
  {
    "BID": 6504036,
    "BeerName": "Cotted Sow",
    "BeerStyle": "Farmhouse Ale - Other",
    "BreweryName": "WildManDan Brewery",
    "Origin": "Afton, VA United States",
    "BeerAbv": 3.90,
    "BeerIbu": 37.00,
    "BeerLabel": "https://assets.untappd.com/site/beer_logos/beer-5955108_a080a_sm.jpeg",
    "HallRating": 13.82,
    "BAR": 4.73,
    "StylePlus": "96",
    "RatingScore": 3.66,
    "AdjustedRating": "2.1196323716875209334179834932"
  },
  {
    "BID": 3223503,
    "BeerName": "Yellow Fizzy Beer",
    "BeerStyle": "Pilsner - New Zealand",
    "BreweryName": "Prospect Point Brewing",
    "Origin": "Frederick, MD United States",
    "BeerAbv": 4.80,
    "BeerIbu": 24.00,
    "BeerLabel": "https://assets.untappd.com/site/brewery_logos/brewery-430856_4e1ad.jpeg",
    "HallRating": 13.82,
    "BAR": 6.55,
    "StylePlus": "97",
    "RatingScore": 3.64,
    "AdjustedRating": "2.1209156454396291865729976499"
  },
  {
    "BID": 5609957,
    "BeerName": "Collines De Bonne Double IPA",
    "BeerStyle": "IPA - Imperial / Double",
    "BreweryName": "Brasseurs des Collines",
    "Origin": "Chelsea, QC Canada",
    "BeerAbv": 9.00,
    "BeerIbu": 70.00,
    "BeerLabel": "https://assets.untappd.com/site/beer_logos/beer-5609957_eeb42_sm.jpeg",
    "HallRating": 13.82,
    "BAR": 4.72,
    "StylePlus": "92",
    "RatingScore": 3.56,
    "AdjustedRating": "2.1196092752145212046681013905"
  },
  {
    "BID": 4961243,
    "BeerName": "Cheluna Colada",
    "BeerStyle": "IPA - Milkshake",
    "BreweryName": "Cheluna Brewing Company",
    "Origin": "Aurora, CO United States",
    "BeerAbv": 7.80,
    "BeerIbu": 35.00,
    "BeerLabel": "https://assets.untappd.com/site/brewery_logos/brewery-311176_05063.jpeg",
    "HallRating": 13.82,
    "BAR": 4.72,
    "StylePlus": "105",
    "RatingScore": 4.02,
    "AdjustedRating": "2.119697808171926904070966339"
  },
  {
    "BID": 5200833,
    "BeerName": "Infinite Monkey Theorem",
    "BeerStyle": "Stout - Imperial / Double Pastry",
    "BreweryName": "Hop Hooligans",
    "Origin": "Jilava, Ilfov Romania",
    "BeerAbv": 11.00,
    "BeerIbu": 20.00,
    "BeerLabel": "https://assets.untappd.com/site/beer_logos/beer-4814275_07cb2_sm.jpeg",
    "HallRating": 13.82,
    "BAR": 6.55,
    "StylePlus": "96",
    "RatingScore": 3.98,
    "AdjustedRating": "2.1212604422911229599290735862"
  }
]
